<?xml version="1.0" encoding="UTF-8" standalone="yes"?><result><status>000</status><message>정상</message><list><rcept_no>20220513001393</rcept_no><reprt_code>11013</reprt_code><bsns_year>2022</bsns_year><corp_code>00508344</corp_code><sj_div>BS</sj_div><sj_nm>재무상태표</sj_nm><account_id>ifrs-full_CurrentAssets</account_id><account_nm>유동자산</account_nm><account_detail>-</account_detail><thstrm_nm>제 19 기 1분기말</thstrm_nm><thstrm_amount>1435500297231</thstrm_amount><frmtrm_nm>제 18 기말</frmtrm_nm><frmtrm_amount>1179715303078</frmtrm_amount><ord>1</ord><currency>KRW</currency></list><list><rcept_no>20220513001393</rcept_no><reprt_code>11013</reprt_code><bsns_year>2022</bsns_year><corp_code>00508344</corp_code><sj_div>BS</sj_div><sj_nm>재무상태표</sj_nm><account_id>ifrs-full_CashAndCashEquivalents</account_id><account_nm>현금및현금성자산</account_nm><account_detail>-</account_detail><thstrm_nm>제 19 기 1분기말</thstrm_nm><thstrm_amount>79093300671</thstrm_amount><frmtrm_nm>제 18 기말</frmtrm_nm><frmtrm_amount>70925668936</frmtrm_amount><ord>2</ord><currency>KRW</currency></list><list><rcept_no>20220513001393</rcept_no><reprt_code>11013</reprt_code><bsns_year>2022</bsns_year><corp_code>00508344</corp_code><sj_div>BS</sj_div><sj_nm>재무상태표</sj_nm><account_id>dart_ShortTermDepositsNotClassifiedAsCashEquivalents</account_id><account_nm>단기금융상품</account_nm><account_detail>-</account_detail><thstrm_nm>제 19 기 1분기말</thstrm_nm><thstrm_amount>173572022964</thstrm_amount><frmtrm_nm>제 18 기말</frmtrm_nm><frmtrm_amount>54252127772</frmtrm_amount><ord>3</ord><currency>KRW</currency></list><list><rcept_no>20220513001393</rcept_no><reprt_code>11013</reprt_code><bsns_year>2022</bsns_year><corp_code>00508344</corp_code><sj_div>BS</sj_div><sj_nm>재무상태표</sj_nm><account_id>dart_ShortTermLoans</account_id><account_nm>단기대여금</account_nm><account_detail>-</account_detail><thstrm_nm>제 19 기 1분기말</thstrm_nm><thstrm_amount>15908682742</thstrm_amount><frmtrm_nm>제 18 기말</frmtrm_nm><frmtrm_amount>20364431062</frmtrm_amount><ord>4</ord><currency>KRW</currency></list><list><rcept_no>20220513001393</rcept_no><reprt_code>11013</reprt_code><bsns_year>2022</bsns_year><corp_code>00508344</corp_code><sj_div>BS</sj_div><sj_nm>재무상태표</sj_nm><account_id>-표준계정코드 미사용-</account_id><account_nm>유동성장기대여금</account_nm><account_detail>-</account_detail><thstrm_nm>제 19 기 1분기말</thstrm_nm><thstrm_amount>4182244000</thstrm_amount><frmtrm_nm>제 18 기말</frmtrm_nm><frmtrm_amount>2516492000</frmtrm_amount><ord>5</ord><currency>KRW</currency></list><list><rcept_no>20220513001393</rcept_no><reprt_code>11013</reprt_code><bsns_year>2022</bsns_year><corp_code>00508344</corp_code><sj_div>BS</sj_div><sj_nm>재무상태표</sj_nm><account_id>ifrs-full_TradeAndOtherCurrentReceivables</account_id><account_nm>매출채권및기타채권</account_nm><account_detail>-</account_detail><thstrm_nm>제 19 기 1분기말</thstrm_nm><thstrm_amount>30309851782</thstrm_amount><frmtrm_nm>제 18 기말</frmtrm_nm><frmtrm_amount>40575793039</frmtrm_amount><ord>6</ord><currency>KRW</currency></list><list><rcept_no>20220513001393</rcept_no><reprt_code>11013</reprt_code><bsns_year>2022</bsns_year><corp_code>00508344</corp_code><sj_div>BS</sj_div><sj_nm>재무상태표</sj_nm><account_id>ifrs-full_CurrentContractAssets</account_id><account_nm>계약자산</account_nm><account_detail>-</account_detail><thstrm_nm>제 19 기 1분기말</thstrm_nm><thstrm_amount>70474176555</thstrm_amount><frmtrm_nm>제 18 기말</frmtrm_nm><frmtrm_amount>18803612563</frmtrm_amount><ord>7</ord><currency>KRW</currency></list><list><rcept_no>20220513001393</rcept_no><reprt_code>11013</reprt_code><bsns_year>2022</bsns_year><corp_code>00508344</corp_code><sj_div>BS</sj_div><sj_nm>재무상태표</sj_nm><account_id>ifrs-full_Inventories</account_id><account_nm>재고자산</account_nm><account_detail>-</account_detail><thstrm_nm>제 19 기 1분기말</thstrm_nm><thstrm_amount>977479274465</thstrm_amount><frmtrm_nm>제 18 기말</frmtrm_nm><frmtrm_amount>850441372211</frmtrm_amount><ord>8</ord><currency>KRW</currency></list><list><rcept_no>20220513001393</rcept_no><reprt_code>11013</reprt_code><bsns_year>2022</bsns_year><corp_code>00508344</corp_code><sj_div>BS</sj_div><sj_nm>재무상태표</sj_nm><account_id>-표준계정코드 미사용-</account_id><account_nm>계약원가</account_nm><account_detail>-</account_detail><thstrm_nm>제 19 기 1분기말</thstrm_nm><thstrm_amount>8341332271</thstrm_amount><frmtrm_nm>제 18 기말</frmtrm_nm><frmtrm_amount>6426673128</frmtrm_amount><ord>9</ord><currency>KRW</currency></list><list><rcept_no>20220513001393</rcept_no><reprt_code>11013</reprt_code><bsns_year>2022</bsns_year><corp_code>00508344</corp_code><sj_div>BS</sj_div><sj_nm>재무상태표</sj_nm><account_id>ifrs-full_CurrentTaxAssets</account_id><account_nm>당기법인세자산</account_nm><account_detail>-</account_detail><thstrm_nm>제 19 기 1분기말</thstrm_nm><thstrm_amount>984729980</thstrm_amount><frmtrm_nm>제 18 기말</frmtrm_nm><frmtrm_amount>983399800</frmtrm_amount><ord>10</ord><currency>KRW</currency></list><list><rcept_no>20220513001393</rcept_no><reprt_code>11013</reprt_code><bsns_year>2022</bsns_year><corp_code>00508344</corp_code><sj_div>BS</sj_div><sj_nm>재무상태표</sj_nm><account_id>ifrs-full_OtherCurrentFinancialAssets</account_id><account_nm>기타유동금융자산</account_nm><account_detail>-</account_detail><thstrm_nm>제 19 기 1분기말</thstrm_nm><thstrm_amount>585571925</thstrm_amount><frmtrm_nm>제 18 기말</frmtrm_nm><frmtrm_amount>597764820</frmtrm_amount><ord>11</ord><currency>KRW</currency></list><list><rcept_no>20220513001393</rcept_no><reprt_code>11013</reprt_code><bsns_year>2022</bsns_year><corp_code>00508344</corp_code><sj_div>BS</sj_div><sj_nm>재무상태표</sj_nm><account_id>dart_OtherCurrentAssets</account_id><account_nm>기타유동자산</account_nm><account_detail>-</account_detail><thstrm_nm>제 19 기 1분기말</thstrm_nm><thstrm_amount>72791860918</thstrm_amount><frmtrm_nm>제 18 기말</frmtrm_nm><frmtrm_amount>113068395890</frmtrm_amount><ord>12</ord><currency>KRW</currency></list><list><rcept_no>20220513001393</rcept_no><reprt_code>11013</reprt_code><bsns_year>2022</bsns_year><corp_code>00508344</corp_code><sj_div>BS</sj_div><sj_nm>재무상태표</sj_nm><account_id>dart_CurrentDerivativeAsset</account_id><account_nm>파생상품자산</account_nm><account_detail>-</account_detail><thstrm_nm>제 19 기 1분기말</thstrm_nm><thstrm_amount>1723219849</thstrm_amount><frmtrm_nm>제 18 기말</frmtrm_nm><frmtrm_amount>759571857</frmtrm_amount><ord>13</ord><currency>KRW</currency></list><list><rcept_no>20220513001393</rcept_no><reprt_code>11013</reprt_code><bsns_year>2022</bsns_year><corp_code>00508344</corp_code><sj_div>BS</sj_div><sj_nm>재무상태표</sj_nm><account_id>dart_CurrentFirmCommitmentAsset</account_id><account_nm>유동확정계약자산</account_nm><account_detail>-</account_detail><thstrm_nm>제 19 기 1분기말</thstrm_nm><thstrm_amount>54029109</thstrm_amount><frmtrm_nm>제 18 기말</frmtrm_nm><frmtrm_amount></frmtrm_amount><ord>14</ord><currency>KRW</currency></list><list><rcept_no>20220513001393</rcept_no><reprt_code>11013</reprt_code><bsns_year>2022</bsns_year><corp_code>00508344</corp_code><sj_div>BS</sj_div><sj_nm>재무상태표</sj_nm><account_id>ifrs-full_NoncurrentAssets</account_id><account_nm>비유동자산</account_nm><account_detail>-</account_detail><thstrm_nm>제 19 기 1분기말</thstrm_nm><thstrm_amount>869900679018</thstrm_amount><frmtrm_nm>제 18 기말</frmtrm_nm><frmtrm_amount>803715464961</frmtrm_amount><ord>15</ord><currency>KRW</currency></list><list><rcept_no>20220513001393</rcept_no><reprt_code>11013</reprt_code><bsns_year>2022</bsns_year><corp_code>00508344</corp_code><sj_div>BS</sj_div><sj_nm>재무상태표</sj_nm><account_id>dart_LongTermTradeAndOtherNonCurrentReceivablesGross</account_id><account_nm>장기매출채권및기타채권</account_nm><account_detail>-</account_detail><thstrm_nm>제 19 기 1분기말</thstrm_nm><thstrm_amount>3050329458</thstrm_amount><frmtrm_nm>제 18 기말</frmtrm_nm><frmtrm_amount>3518544711</frmtrm_amount><ord>16</ord><currency>KRW</currency></list><list><rcept_no>20220513001393</rcept_no><reprt_code>11013</reprt_code><bsns_year>2022</bsns_year><corp_code>00508344</corp_code><sj_div>BS</sj_div><sj_nm>재무상태표</sj_nm><account_id>dart_LongTermDepositsNotClassifiedAsCashEquivalents</account_id><account_nm>장기금융상품</account_nm><account_detail>-</account_detail><thstrm_nm>제 19 기 1분기말</thstrm_nm><thstrm_amount>30756094830</thstrm_amount><frmtrm_nm>제 18 기말</frmtrm_nm><frmtrm_amount>63662384262</frmtrm_amount><ord>17</ord><currency>KRW</currency></list><list><rcept_no>20220513001393</rcept_no><reprt_code>11013</reprt_code><bsns_year>2022</bsns_year><corp_code>00508344</corp_code><sj_div>BS</sj_div><sj_nm>재무상태표</sj_nm><account_id>-표준계정코드 미사용-</account_id><account_nm>장기투자자산</account_nm><account_detail>-</account_detail><thstrm_nm>제 19 기 1분기말</thstrm_nm><thstrm_amount>67718164597</thstrm_amount><frmtrm_nm>제 18 기말</frmtrm_nm><frmtrm_amount>67885495454</frmtrm_amount><ord>18</ord><currency>KRW</currency></list><list><rcept_no>20220513001393</rcept_no><reprt_code>11013</reprt_code><bsns_year>2022</bsns_year><corp_code>00508344</corp_code><sj_div>BS</sj_div><sj_nm>재무상태표</sj_nm><account_id>ifrs-full_InvestmentsInAssociates</account_id><account_nm>공동기업및관계기업투자</account_nm><account_detail>-</account_detail><thstrm_nm>제 19 기 1분기말</thstrm_nm><thstrm_amount>227848759962</thstrm_amount><frmtrm_nm>제 18 기말</frmtrm_nm><frmtrm_amount>156397285005</frmtrm_amount><ord>19</ord><currency>KRW</currency></list><list><rcept_no>20220513001393</rcept_no><reprt_code>11013</reprt_code><bsns_year>2022</bsns_year><corp_code>00508344</corp_code><sj_div>BS</sj_div><sj_nm>재무상태표</sj_nm><account_id>dart_LongTermLoansGross</account_id><account_nm>장기대여금</account_nm><account_detail>-</account_detail><thstrm_nm>제 19 기 1분기말</thstrm_nm><thstrm_amount>14852532234</thstrm_amount><frmtrm_nm>제 18 기말</frmtrm_nm><frmtrm_amount>15730289745</frmtrm_amount><ord>20</ord><currency>KRW</currency></list><list><rcept_no>20220513001393</rcept_no><reprt_code>11013</reprt_code><bsns_year>2022</bsns_year><corp_code>00508344</corp_code><sj_div>BS</sj_div><sj_nm>재무상태표</sj_nm><account_id>ifrs-full_PropertyPlantAndEquipment</account_id><account_nm>유형자산</account_nm><account_detail>-</account_detail><thstrm_nm>제 19 기 1분기말</thstrm_nm><thstrm_amount>382846941191</thstrm_amount><frmtrm_nm>제 18 기말</frmtrm_nm><frmtrm_amount>356566387249</frmtrm_amount><ord>21</ord><currency>KRW</currency></list><list><rcept_no>20220513001393</rcept_no><reprt_code>11013</reprt_code><bsns_year>2022</bsns_year><corp_code>00508344</corp_code><sj_div>BS</sj_div><sj_nm>재무상태표</sj_nm><account_id>ifrs-full_RightofuseAssets</account_id><account_nm>사용권자산</account_nm><account_detail>-</account_detail><thstrm_nm>제 19 기 1분기말</thstrm_nm><thstrm_amount>8830731431</thstrm_amount><frmtrm_nm>제 18 기말</frmtrm_nm><frmtrm_amount>9072194405</frmtrm_amount><ord>22</ord><currency>KRW</currency></list><list><rcept_no>20220513001393</rcept_no><reprt_code>11013</reprt_code><bsns_year>2022</bsns_year><corp_code>00508344</corp_code><sj_div>BS</sj_div><sj_nm>재무상태표</sj_nm><account_id>ifrs-full_InvestmentProperty</account_id><account_nm>투자부동산</account_nm><account_detail>-</account_detail><thstrm_nm>제 19 기 1분기말</thstrm_nm><thstrm_amount>91089925458</thstrm_amount><frmtrm_nm>제 18 기말</frmtrm_nm><frmtrm_amount>83846044947</frmtrm_amount><ord>23</ord><currency>KRW</currency></list><list><rcept_no>20220513001393</rcept_no><reprt_code>11013</reprt_code><bsns_year>2022</bsns_year><corp_code>00508344</corp_code><sj_div>BS</sj_div><sj_nm>재무상태표</sj_nm><account_id>dart_OtherIntangibleAssetsGross</account_id><account_nm>무형자산</account_nm><account_detail>-</account_detail><thstrm_nm>제 19 기 1분기말</thstrm_nm><thstrm_amount>18489652901</thstrm_amount><frmtrm_nm>제 18 기말</frmtrm_nm><frmtrm_amount>18828457661</frmtrm_amount><ord>24</ord><currency>KRW</currency></list><list><rcept_no>20220513001393</rcept_no><reprt_code>11013</reprt_code><bsns_year>2022</bsns_year><corp_code>00508344</corp_code><sj_div>BS</sj_div><sj_nm>재무상태표</sj_nm><account_id>ifrs-full_OtherNoncurrentFinancialAssets</account_id><account_nm>기타비유동금융자산</account_nm><account_detail>-</account_detail><thstrm_nm>제 19 기 1분기말</thstrm_nm><thstrm_amount>4265800994</thstrm_amount><frmtrm_nm>제 18 기말</frmtrm_nm><frmtrm_amount>5075911123</frmtrm_amount><ord>25</ord><currency>KRW</currency></list><list><rcept_no>20220513001393</rcept_no><reprt_code>11013</reprt_code><bsns_year>2022</bsns_year><corp_code>00508344</corp_code><sj_div>BS</sj_div><sj_nm>재무상태표</sj_nm><account_id>dart_OtherNonCurrentAssets</account_id><account_nm>기타비유동자산</account_nm><account_detail>-</account_detail><thstrm_nm>제 19 기 1분기말</thstrm_nm><thstrm_amount>2727235857</thstrm_amount><frmtrm_nm>제 18 기말</frmtrm_nm><frmtrm_amount>2637810429</frmtrm_amount><ord>26</ord><currency>KRW</currency></list><list><rcept_no>20220513001393</rcept_no><reprt_code>11013</reprt_code><bsns_year>2022</bsns_year><corp_code>00508344</corp_code><sj_div>BS</sj_div><sj_nm>재무상태표</sj_nm><account_id>dart_NonCurrentDerivativeAssets</account_id><account_nm>파생상품자산</account_nm><account_detail>-</account_detail><thstrm_nm>제 19 기 1분기말</thstrm_nm><thstrm_amount>7729762412</thstrm_amount><frmtrm_nm>제 18 기말</frmtrm_nm><frmtrm_amount>5669879953</frmtrm_amount><ord>27</ord><currency>KRW</currency></list><list><rcept_no>20220513001393</rcept_no><reprt_code>11013</reprt_code><bsns_year>2022</bsns_year><corp_code>00508344</corp_code><sj_div>BS</sj_div><sj_nm>재무상태표</sj_nm><account_id>ifrs-full_DeferredTaxAssets</account_id><account_nm>이연법인세자산</account_nm><account_detail>-</account_detail><thstrm_nm>제 19 기 1분기말</thstrm_nm><thstrm_amount>9694747693</thstrm_amount><frmtrm_nm>제 18 기말</frmtrm_nm><frmtrm_amount>14824780017</frmtrm_amount><ord>28</ord><currency>KRW</currency></list><list><rcept_no>20220513001393</rcept_no><reprt_code>11013</reprt_code><bsns_year>2022</bsns_year><corp_code>00508344</corp_code><sj_div>BS</sj_div><sj_nm>재무상태표</sj_nm><account_id>ifrs-full_Assets</account_id><account_nm>자산총계</account_nm><account_detail>-</account_detail><thstrm_nm>제 19 기 1분기말</thstrm_nm><thstrm_amount>2305400976249</thstrm_amount><frmtrm_nm>제 18 기말</frmtrm_nm><frmtrm_amount>1983430768039</frmtrm_amount><ord>29</ord><currency>KRW</currency></list><list><rcept_no>20220513001393</rcept_no><reprt_code>11013</reprt_code><bsns_year>2022</bsns_year><corp_code>00508344</corp_code><sj_div>BS</sj_div><sj_nm>재무상태표</sj_nm><account_id>ifrs-full_CurrentLiabilities</account_id><account_nm>유동부채</account_nm><account_detail>-</account_detail><thstrm_nm>제 19 기 1분기말</thstrm_nm><thstrm_amount>613879709581</thstrm_amount><frmtrm_nm>제 18 기말</frmtrm_nm><frmtrm_amount>465594239957</frmtrm_amount><ord>31</ord><currency>KRW</currency></list><list><rcept_no>20220513001393</rcept_no><reprt_code>11013</reprt_code><bsns_year>2022</bsns_year><corp_code>00508344</corp_code><sj_div>BS</sj_div><sj_nm>재무상태표</sj_nm><account_id>ifrs-full_TradeAndOtherCurrentPayables</account_id><account_nm>매입채무및기타채무</account_nm><account_detail>-</account_detail><thstrm_nm>제 19 기 1분기말</thstrm_nm><thstrm_amount>119580304727</thstrm_amount><frmtrm_nm>제 18 기말</frmtrm_nm><frmtrm_amount>45120026865</frmtrm_amount><ord>32</ord><currency>KRW</currency></list><list><rcept_no>20220513001393</rcept_no><reprt_code>11013</reprt_code><bsns_year>2022</bsns_year><corp_code>00508344</corp_code><sj_div>BS</sj_div><sj_nm>재무상태표</sj_nm><account_id>ifrs-full_ShorttermBorrowings</account_id><account_nm>단기차입금</account_nm><account_detail>-</account_detail><thstrm_nm>제 19 기 1분기말</thstrm_nm><thstrm_amount>8000000000</thstrm_amount><frmtrm_nm>제 18 기말</frmtrm_nm><frmtrm_amount>46000000000</frmtrm_amount><ord>33</ord><currency>KRW</currency></list><list><rcept_no>20220513001393</rcept_no><reprt_code>11013</reprt_code><bsns_year>2022</bsns_year><corp_code>00508344</corp_code><sj_div>BS</sj_div><sj_nm>재무상태표</sj_nm><account_id>ifrs-full_CurrentPortionOfLongtermBorrowings</account_id><account_nm>유동성장기차입금</account_nm><account_detail>-</account_detail><thstrm_nm>제 19 기 1분기말</thstrm_nm><thstrm_amount>330508215580</thstrm_amount><frmtrm_nm>제 18 기말</frmtrm_nm><frmtrm_amount>242779375113</frmtrm_amount><ord>34</ord><currency>KRW</currency></list><list><rcept_no>20220513001393</rcept_no><reprt_code>11013</reprt_code><bsns_year>2022</bsns_year><corp_code>00508344</corp_code><sj_div>BS</sj_div><sj_nm>재무상태표</sj_nm><account_id>dart_CurrentPortionOfBonds</account_id><account_nm>유동성사채</account_nm><account_detail>-</account_detail><thstrm_nm>제 19 기 1분기말</thstrm_nm><thstrm_amount>76241966130</thstrm_amount><frmtrm_nm>제 18 기말</frmtrm_nm><frmtrm_amount>75417364993</frmtrm_amount><ord>35</ord><currency>KRW</currency></list><list><rcept_no>20220513001393</rcept_no><reprt_code>11013</reprt_code><bsns_year>2022</bsns_year><corp_code>00508344</corp_code><sj_div>BS</sj_div><sj_nm>재무상태표</sj_nm><account_id>ifrs-full_CurrentProvisions</account_id><account_nm>충당부채</account_nm><account_detail>-</account_detail><thstrm_nm>제 19 기 1분기말</thstrm_nm><thstrm_amount>177070910</thstrm_amount><frmtrm_nm>제 18 기말</frmtrm_nm><frmtrm_amount>177070910</frmtrm_amount><ord>36</ord><currency>KRW</currency></list><list><rcept_no>20220513001393</rcept_no><reprt_code>11013</reprt_code><bsns_year>2022</bsns_year><corp_code>00508344</corp_code><sj_div>BS</sj_div><sj_nm>재무상태표</sj_nm><account_id>dart_PaymentsOfIncomeTaxesPayable</account_id><account_nm>미지급법인세</account_nm><account_detail>-</account_detail><thstrm_nm>제 19 기 1분기말</thstrm_nm><thstrm_amount>25146289812</thstrm_amount><frmtrm_nm>제 18 기말</frmtrm_nm><frmtrm_amount>27207949710</frmtrm_amount><ord>37</ord><currency>KRW</currency></list><list><rcept_no>20220513001393</rcept_no><reprt_code>11013</reprt_code><bsns_year>2022</bsns_year><corp_code>00508344</corp_code><sj_div>BS</sj_div><sj_nm>재무상태표</sj_nm><account_id>ifrs-full_OtherCurrentFinancialLiabilities</account_id><account_nm>기타유동금융부채</account_nm><account_detail>-</account_detail><thstrm_nm>제 19 기 1분기말</thstrm_nm><thstrm_amount>24004808295</thstrm_amount><frmtrm_nm>제 18 기말</frmtrm_nm><frmtrm_amount>2844978144</frmtrm_amount><ord>38</ord><currency>KRW</currency></list><list><rcept_no>20220513001393</rcept_no><reprt_code>11013</reprt_code><bsns_year>2022</bsns_year><corp_code>00508344</corp_code><sj_div>BS</sj_div><sj_nm>재무상태표</sj_nm><account_id>dart_OtherCurrentLiabilities</account_id><account_nm>기타유동부채</account_nm><account_detail>-</account_detail><thstrm_nm>제 19 기 1분기말</thstrm_nm><thstrm_amount>30167025018</thstrm_amount><frmtrm_nm>제 18 기말</frmtrm_nm><frmtrm_amount>26047474222</frmtrm_amount><ord>39</ord><currency>KRW</currency></list><list><rcept_no>20220513001393</rcept_no><reprt_code>11013</reprt_code><bsns_year>2022</bsns_year><corp_code>00508344</corp_code><sj_div>BS</sj_div><sj_nm>재무상태표</sj_nm><account_id>dart_CurrentDerivativeLiabilities</account_id><account_nm>유동파생상품부채</account_nm><account_detail>-</account_detail><thstrm_nm>제 19 기 1분기말</thstrm_nm><thstrm_amount>54029109</thstrm_amount><frmtrm_nm>제 18 기말</frmtrm_nm><frmtrm_amount></frmtrm_amount><ord>40</ord><currency>KRW</currency></list><list><rcept_no>20220513001393</rcept_no><reprt_code>11013</reprt_code><bsns_year>2022</bsns_year><corp_code>00508344</corp_code><sj_div>BS</sj_div><sj_nm>재무상태표</sj_nm><account_id>ifrs-full_NoncurrentLiabilities</account_id><account_nm>비유동부채</account_nm><account_detail>-</account_detail><thstrm_nm>제 19 기 1분기말</thstrm_nm><thstrm_amount>1032679308517</thstrm_amount><frmtrm_nm>제 18 기말</frmtrm_nm><frmtrm_amount>878580480330</frmtrm_amount><ord>41</ord><currency>KRW</currency></list><list><rcept_no>20220513001393</rcept_no><reprt_code>11013</reprt_code><bsns_year>2022</bsns_year><corp_code>00508344</corp_code><sj_div>BS</sj_div><sj_nm>재무상태표</sj_nm><account_id>dart_LongTermTradeAndOtherNonCurrentPayables</account_id><account_nm>장기성매입채무및기타채무</account_nm><account_detail>-</account_detail><thstrm_nm>제 19 기 1분기말</thstrm_nm><thstrm_amount>77502855315</thstrm_amount><frmtrm_nm>제 18 기말</frmtrm_nm><frmtrm_amount>77654968562</frmtrm_amount><ord>42</ord><currency>KRW</currency></list><list><rcept_no>20220513001393</rcept_no><reprt_code>11013</reprt_code><bsns_year>2022</bsns_year><corp_code>00508344</corp_code><sj_div>BS</sj_div><sj_nm>재무상태표</sj_nm><account_id>dart_LongTermBorrowingsGross</account_id><account_nm>장기차입금</account_nm><account_detail>-</account_detail><thstrm_nm>제 19 기 1분기말</thstrm_nm><thstrm_amount>621992104875</thstrm_amount><frmtrm_nm>제 18 기말</frmtrm_nm><frmtrm_amount>518218040298</frmtrm_amount><ord>43</ord><currency>KRW</currency></list><list><rcept_no>20220513001393</rcept_no><reprt_code>11013</reprt_code><bsns_year>2022</bsns_year><corp_code>00508344</corp_code><sj_div>BS</sj_div><sj_nm>재무상태표</sj_nm><account_id>dart_BondsIssued</account_id><account_nm>사채</account_nm><account_detail>-</account_detail><thstrm_nm>제 19 기 1분기말</thstrm_nm><thstrm_amount>302526087497</thstrm_amount><frmtrm_nm>제 18 기말</frmtrm_nm><frmtrm_amount>251574234093</frmtrm_amount><ord>44</ord><currency>KRW</currency></list><list><rcept_no>20220513001393</rcept_no><reprt_code>11013</reprt_code><bsns_year>2022</bsns_year><corp_code>00508344</corp_code><sj_div>BS</sj_div><sj_nm>재무상태표</sj_nm><account_id>ifrs-full_NoncurrentProvisions</account_id><account_nm>충당부채</account_nm><account_detail>-</account_detail><thstrm_nm>제 19 기 1분기말</thstrm_nm><thstrm_amount>5272601162</thstrm_amount><frmtrm_nm>제 18 기말</frmtrm_nm><frmtrm_amount>6859086593</frmtrm_amount><ord>45</ord><currency>KRW</currency></list><list><rcept_no>20220513001393</rcept_no><reprt_code>11013</reprt_code><bsns_year>2022</bsns_year><corp_code>00508344</corp_code><sj_div>BS</sj_div><sj_nm>재무상태표</sj_nm><account_id>dart_PostemploymentBenefitObligations</account_id><account_nm>순확정급여부채</account_nm><account_detail>-</account_detail><thstrm_nm>제 19 기 1분기말</thstrm_nm><thstrm_amount>1894428238</thstrm_amount><frmtrm_nm>제 18 기말</frmtrm_nm><frmtrm_amount>1027784237</frmtrm_amount><ord>46</ord><currency>KRW</currency></list><list><rcept_no>20220513001393</rcept_no><reprt_code>11013</reprt_code><bsns_year>2022</bsns_year><corp_code>00508344</corp_code><sj_div>BS</sj_div><sj_nm>재무상태표</sj_nm><account_id>-표준계정코드 미사용-</account_id><account_nm>미지급법인세</account_nm><account_detail>-</account_detail><thstrm_nm>제 19 기 1분기말</thstrm_nm><thstrm_amount>4738298006</thstrm_amount><frmtrm_nm>제 18 기말</frmtrm_nm><frmtrm_amount>5062081076</frmtrm_amount><ord>47</ord><currency>KRW</currency></list><list><rcept_no>20220513001393</rcept_no><reprt_code>11013</reprt_code><bsns_year>2022</bsns_year><corp_code>00508344</corp_code><sj_div>BS</sj_div><sj_nm>재무상태표</sj_nm><account_id>ifrs-full_DeferredTaxLiabilities</account_id><account_nm>이연법인세부채</account_nm><account_detail>-</account_detail><thstrm_nm>제 19 기 1분기말</thstrm_nm><thstrm_amount>5239540184</thstrm_amount><frmtrm_nm>제 18 기말</frmtrm_nm><frmtrm_amount>5121090496</frmtrm_amount><ord>48</ord><currency>KRW</currency></list><list><rcept_no>20220513001393</rcept_no><reprt_code>11013</reprt_code><bsns_year>2022</bsns_year><corp_code>00508344</corp_code><sj_div>BS</sj_div><sj_nm>재무상태표</sj_nm><account_id>dart_NonCurrentDerivativeLiabilities</account_id><account_nm>파생상품부채</account_nm><account_detail>-</account_detail><thstrm_nm>제 19 기 1분기말</thstrm_nm><thstrm_amount>1674000000</thstrm_amount><frmtrm_nm>제 18 기말</frmtrm_nm><frmtrm_amount>1674000000</frmtrm_amount><ord>49</ord><currency>KRW</currency></list><list><rcept_no>20220513001393</rcept_no><reprt_code>11013</reprt_code><bsns_year>2022</bsns_year><corp_code>00508344</corp_code><sj_div>BS</sj_div><sj_nm>재무상태표</sj_nm><account_id>ifrs-full_OtherNoncurrentFinancialLiabilities</account_id><account_nm>기타비유동금융부채</account_nm><account_detail>-</account_detail><thstrm_nm>제 19 기 1분기말</thstrm_nm><thstrm_amount>11839393240</thstrm_amount><frmtrm_nm>제 18 기말</frmtrm_nm><frmtrm_amount>11389194975</frmtrm_amount><ord>50</ord><currency>KRW</currency></list><list><rcept_no>20220513001393</rcept_no><reprt_code>11013</reprt_code><bsns_year>2022</bsns_year><corp_code>00508344</corp_code><sj_div>BS</sj_div><sj_nm>재무상태표</sj_nm><account_id>ifrs-full_Liabilities</account_id><account_nm>부채총계</account_nm><account_detail>-</account_detail><thstrm_nm>제 19 기 1분기말</thstrm_nm><thstrm_amount>1646559018098</thstrm_amount><frmtrm_nm>제 18 기말</frmtrm_nm><frmtrm_amount>1344174720287</frmtrm_amount><ord>51</ord><currency>KRW</currency></list><list><rcept_no>20220513001393</rcept_no><reprt_code>11013</reprt_code><bsns_year>2022</bsns_year><corp_code>00508344</corp_code><sj_div>BS</sj_div><sj_nm>재무상태표</sj_nm><account_id>ifrs-full_EquityAttributableToOwnersOfParent</account_id><account_nm>지배기업의 소유주에게 귀속되는 자본</account_nm><account_detail>-</account_detail><thstrm_nm>제 19 기 1분기말</thstrm_nm><thstrm_amount>658841958151</thstrm_amount><frmtrm_nm>제 18 기말</frmtrm_nm><frmtrm_amount>639256047752</frmtrm_amount><ord>53</ord><currency>KRW</currency></list><list><rcept_no>20220513001393</rcept_no><reprt_code>11013</reprt_code><bsns_year>2022</bsns_year><corp_code>00508344</corp_code><sj_div>BS</sj_div><sj_nm>재무상태표</sj_nm><account_id>ifrs-full_IssuedCapital</account_id><account_nm>자본금</account_nm><account_detail>-</account_detail><thstrm_nm>제 19 기 1분기말</thstrm_nm><thstrm_amount>24190164000</thstrm_amount><frmtrm_nm>제 18 기말</frmtrm_nm><frmtrm_amount>24190164000</frmtrm_amount><ord>54</ord><currency>KRW</currency></list><list><rcept_no>20220513001393</rcept_no><reprt_code>11013</reprt_code><bsns_year>2022</bsns_year><corp_code>00508344</corp_code><sj_div>BS</sj_div><sj_nm>재무상태표</sj_nm><account_id>dart_CapitalSurplus</account_id><account_nm>자본잉여금</account_nm><account_detail>-</account_detail><thstrm_nm>제 19 기 1분기말</thstrm_nm><thstrm_amount>290804582279</thstrm_amount><frmtrm_nm>제 18 기말</frmtrm_nm><frmtrm_amount>290804582279</frmtrm_amount><ord>55</ord><currency>KRW</currency></list><list><rcept_no>20220513001393</rcept_no><reprt_code>11013</reprt_code><bsns_year>2022</bsns_year><corp_code>00508344</corp_code><sj_div>BS</sj_div><sj_nm>재무상태표</sj_nm><account_id>dart_ElementsOfOtherStockholdersEquity</account_id><account_nm>기타자본</account_nm><account_detail>-</account_detail><thstrm_nm>제 19 기 1분기말</thstrm_nm><thstrm_amount>3302794697</thstrm_amount><frmtrm_nm>제 18 기말</frmtrm_nm><frmtrm_amount>-3940549139</frmtrm_amount><ord>56</ord><currency>KRW</currency></list><list><rcept_no>20220513001393</rcept_no><reprt_code>11013</reprt_code><bsns_year>2022</bsns_year><corp_code>00508344</corp_code><sj_div>BS</sj_div><sj_nm>재무상태표</sj_nm><account_id>dart_OtherComprehensiveIncomeLossAccumulatedAmount</account_id><account_nm>기타포괄손익누계액</account_nm><account_detail>-</account_detail><thstrm_nm>제 19 기 1분기말</thstrm_nm><thstrm_amount>846105379</thstrm_amount><frmtrm_nm>제 18 기말</frmtrm_nm><frmtrm_amount>113949643</frmtrm_amount><ord>57</ord><currency>KRW</currency></list><list><rcept_no>20220513001393</rcept_no><reprt_code>11013</reprt_code><bsns_year>2022</bsns_year><corp_code>00508344</corp_code><sj_div>BS</sj_div><sj_nm>재무상태표</sj_nm><account_id>ifrs-full_RetainedEarnings</account_id><account_nm>이익잉여금</account_nm><account_detail>-</account_detail><thstrm_nm>제 19 기 1분기말</thstrm_nm><thstrm_amount>339698311796</thstrm_amount><frmtrm_nm>제 18 기말</frmtrm_nm><frmtrm_amount>328087900969</frmtrm_amount><ord>58</ord><currency>KRW</currency></list><list><rcept_no>20220513001393</rcept_no><reprt_code>11013</reprt_code><bsns_year>2022</bsns_year><corp_code>00508344</corp_code><sj_div>BS</sj_div><sj_nm>재무상태표</sj_nm><account_id>ifrs-full_Equity</account_id><account_nm>자본총계</account_nm><account_detail>-</account_detail><thstrm_nm>제 19 기 1분기말</thstrm_nm><thstrm_amount>658841958151</thstrm_amount><frmtrm_nm>제 18 기말</frmtrm_nm><frmtrm_amount>639256047752</frmtrm_amount><ord>59</ord><currency>KRW</currency></list><list><rcept_no>20220513001393</rcept_no><reprt_code>11013</reprt_code><bsns_year>2022</bsns_year><corp_code>00508344</corp_code><sj_div>BS</sj_div><sj_nm>재무상태표</sj_nm><account_id>ifrs-full_EquityAndLiabilities</account_id><account_nm>자본과부채총계</account_nm><account_detail>-</account_detail><thstrm_nm>제 19 기 1분기말</thstrm_nm><thstrm_amount>2305400976249</thstrm_amount><frmtrm_nm>제 18 기말</frmtrm_nm><frmtrm_amount>1983430768039</frmtrm_amount><ord>60</ord><currency>KRW</currency></list><list><rcept_no>20220513001393</rcept_no><reprt_code>11013</reprt_code><bsns_year>2022</bsns_year><corp_code>00508344</corp_code><sj_div>CIS</sj_div><sj_nm>포괄손익계산서</sj_nm><account_id>ifrs-full_Revenue</account_id><account_nm>매출액</account_nm><account_detail>-</account_detail><thstrm_nm>제 19 기 1분기</thstrm_nm><thstrm_amount>144438492550</thstrm_amount><thstrm_add_amount>144438492550</thstrm_add_amount><frmtrm_q_nm>제 18 기 1분기</frmtrm_q_nm><frmtrm_q_amount>288671961726</frmtrm_q_amount><frmtrm_add_amount>288671961726</frmtrm_add_amount><ord>0</ord><currency>KRW</currency></list><list><rcept_no>20220513001393</rcept_no><reprt_code>11013</reprt_code><bsns_year>2022</bsns_year><corp_code>00508344</corp_code><sj_div>CIS</sj_div><sj_nm>포괄손익계산서</sj_nm><account_id>ifrs-full_CostOfSales</account_id><account_nm>매출원가</account_nm><account_detail>-</account_detail><thstrm_nm>제 19 기 1분기</thstrm_nm><thstrm_amount>79953681768</thstrm_amount><thstrm_add_amount>79953681768</thstrm_add_amount><frmtrm_q_nm>제 18 기 1분기</frmtrm_q_nm><frmtrm_q_amount>244927070301</frmtrm_q_amount><frmtrm_add_amount>244927070301</frmtrm_add_amount><ord>1</ord><currency>KRW</currency></list><list><rcept_no>20220513001393</rcept_no><reprt_code>11013</reprt_code><bsns_year>2022</bsns_year><corp_code>00508344</corp_code><sj_div>CIS</sj_div><sj_nm>포괄손익계산서</sj_nm><account_id>ifrs-full_GrossProfit</account_id><account_nm>매출총이익</account_nm><account_detail>-</account_detail><thstrm_nm>제 19 기 1분기</thstrm_nm><thstrm_amount>64484810782</thstrm_amount><thstrm_add_amount>64484810782</thstrm_add_amount><frmtrm_q_nm>제 18 기 1분기</frmtrm_q_nm><frmtrm_q_amount>43744891425</frmtrm_q_amount><frmtrm_add_amount>43744891425</frmtrm_add_amount><ord>2</ord><currency>KRW</currency></list><list><rcept_no>20220513001393</rcept_no><reprt_code>11013</reprt_code><bsns_year>2022</bsns_year><corp_code>00508344</corp_code><sj_div>CIS</sj_div><sj_nm>포괄손익계산서</sj_nm><account_id>dart_TotalSellingGeneralAdministrativeExpenses</account_id><account_nm>판매비와관리비</account_nm><account_detail>-</account_detail><thstrm_nm>제 19 기 1분기</thstrm_nm><thstrm_amount>19198943944</thstrm_amount><thstrm_add_amount>19198943944</thstrm_add_amount><frmtrm_q_nm>제 18 기 1분기</frmtrm_q_nm><frmtrm_q_amount>16606752722</frmtrm_q_amount><frmtrm_add_amount>16606752722</frmtrm_add_amount><ord>3</ord><currency>KRW</currency></list><list><rcept_no>20220513001393</rcept_no><reprt_code>11013</reprt_code><bsns_year>2022</bsns_year><corp_code>00508344</corp_code><sj_div>CIS</sj_div><sj_nm>포괄손익계산서</sj_nm><account_id>dart_OperatingIncomeLoss</account_id><account_nm>영업이익</account_nm><account_detail>-</account_detail><thstrm_nm>제 19 기 1분기</thstrm_nm><thstrm_amount>45285866838</thstrm_amount><thstrm_add_amount>45285866838</thstrm_add_amount><frmtrm_q_nm>제 18 기 1분기</frmtrm_q_nm><frmtrm_q_amount>27138138703</frmtrm_q_amount><frmtrm_add_amount>27138138703</frmtrm_add_amount><ord>4</ord><currency>KRW</currency></list><list><rcept_no>20220513001393</rcept_no><reprt_code>11013</reprt_code><bsns_year>2022</bsns_year><corp_code>00508344</corp_code><sj_div>CIS</sj_div><sj_nm>포괄손익계산서</sj_nm><account_id>ifrs-full_FinanceIncome</account_id><account_nm>금융수익</account_nm><account_detail>-</account_detail><thstrm_nm>제 19 기 1분기</thstrm_nm><thstrm_amount>2265226262</thstrm_amount><thstrm_add_amount>2265226262</thstrm_add_amount><frmtrm_q_nm>제 18 기 1분기</frmtrm_q_nm><frmtrm_q_amount>5747930270</frmtrm_q_amount><frmtrm_add_amount>5747930270</frmtrm_add_amount><ord>5</ord><currency>KRW</currency></list><list><rcept_no>20220513001393</rcept_no><reprt_code>11013</reprt_code><bsns_year>2022</bsns_year><corp_code>00508344</corp_code><sj_div>CIS</sj_div><sj_nm>포괄손익계산서</sj_nm><account_id>ifrs-full_FinanceCosts</account_id><account_nm>금융원가</account_nm><account_detail>-</account_detail><thstrm_nm>제 19 기 1분기</thstrm_nm><thstrm_amount>5778172639</thstrm_amount><thstrm_add_amount>5778172639</thstrm_add_amount><frmtrm_q_nm>제 18 기 1분기</frmtrm_q_nm><frmtrm_q_amount>13439599726</frmtrm_q_amount><frmtrm_add_amount>13439599726</frmtrm_add_amount><ord>6</ord><currency>KRW</currency></list><list><rcept_no>20220513001393</rcept_no><reprt_code>11013</reprt_code><bsns_year>2022</bsns_year><corp_code>00508344</corp_code><sj_div>CIS</sj_div><sj_nm>포괄손익계산서</sj_nm><account_id>dart_OtherGains</account_id><account_nm>기타영업외수익</account_nm><account_detail>-</account_detail><thstrm_nm>제 19 기 1분기</thstrm_nm><thstrm_amount>18042062918</thstrm_amount><thstrm_add_amount>18042062918</thstrm_add_amount><frmtrm_q_nm>제 18 기 1분기</frmtrm_q_nm><frmtrm_q_amount>2399132331</frmtrm_q_amount><frmtrm_add_amount>2399132331</frmtrm_add_amount><ord>7</ord><currency>KRW</currency></list><list><rcept_no>20220513001393</rcept_no><reprt_code>11013</reprt_code><bsns_year>2022</bsns_year><corp_code>00508344</corp_code><sj_div>CIS</sj_div><sj_nm>포괄손익계산서</sj_nm><account_id>dart_OtherLosses</account_id><account_nm>기타영업외비용</account_nm><account_detail>-</account_detail><thstrm_nm>제 19 기 1분기</thstrm_nm><thstrm_amount>545069844</thstrm_amount><thstrm_add_amount>545069844</thstrm_add_amount><frmtrm_q_nm>제 18 기 1분기</frmtrm_q_nm><frmtrm_q_amount>1448812027</frmtrm_q_amount><frmtrm_add_amount>1448812027</frmtrm_add_amount><ord>8</ord><currency>KRW</currency></list><list><rcept_no>20220513001393</rcept_no><reprt_code>11013</reprt_code><bsns_year>2022</bsns_year><corp_code>00508344</corp_code><sj_div>CIS</sj_div><sj_nm>포괄손익계산서</sj_nm><account_id>-표준계정코드 미사용-</account_id><account_nm>지분법손실</account_nm><account_detail>-</account_detail><thstrm_nm>제 19 기 1분기</thstrm_nm><thstrm_amount>5813294521</thstrm_amount><thstrm_add_amount>5813294521</thstrm_add_amount><frmtrm_q_nm>제 18 기 1분기</frmtrm_q_nm><frmtrm_q_amount>3538966902</frmtrm_q_amount><frmtrm_add_amount>3538966902</frmtrm_add_amount><ord>9</ord><currency>KRW</currency></list><list><rcept_no>20220513001393</rcept_no><reprt_code>11013</reprt_code><bsns_year>2022</bsns_year><corp_code>00508344</corp_code><sj_div>CIS</sj_div><sj_nm>포괄손익계산서</sj_nm><account_id>ifrs-full_ProfitLossBeforeTax</account_id><account_nm>법인세비용차감전순이익</account_nm><account_detail>-</account_detail><thstrm_nm>제 19 기 1분기</thstrm_nm><thstrm_amount>53456619014</thstrm_amount><thstrm_add_amount>53456619014</thstrm_add_amount><frmtrm_q_nm>제 18 기 1분기</frmtrm_q_nm><frmtrm_q_amount>16857822649</frmtrm_q_amount><frmtrm_add_amount>16857822649</frmtrm_add_amount><ord>10</ord><currency>KRW</currency></list><list><rcept_no>20220513001393</rcept_no><reprt_code>11013</reprt_code><bsns_year>2022</bsns_year><corp_code>00508344</corp_code><sj_div>CIS</sj_div><sj_nm>포괄손익계산서</sj_nm><account_id>ifrs-full_IncomeTaxExpenseContinuingOperations</account_id><account_nm>법인세비용</account_nm><account_detail>-</account_detail><thstrm_nm>제 19 기 1분기</thstrm_nm><thstrm_amount>22282617407</thstrm_amount><thstrm_add_amount>22282617407</thstrm_add_amount><frmtrm_q_nm>제 18 기 1분기</frmtrm_q_nm><frmtrm_q_amount>4131146654</frmtrm_q_amount><frmtrm_add_amount>4131146654</frmtrm_add_amount><ord>11</ord><currency>KRW</currency></list><list><rcept_no>20220513001393</rcept_no><reprt_code>11013</reprt_code><bsns_year>2022</bsns_year><corp_code>00508344</corp_code><sj_div>CIS</sj_div><sj_nm>포괄손익계산서</sj_nm><account_id>-표준계정코드 미사용-</account_id><account_nm>분기순이익</account_nm><account_detail>-</account_detail><thstrm_nm>제 19 기 1분기</thstrm_nm><thstrm_amount>31174001607</thstrm_amount><thstrm_add_amount>31174001607</thstrm_add_amount><frmtrm_q_nm>제 18 기 1분기</frmtrm_q_nm><frmtrm_q_amount>12726675995</frmtrm_q_amount><frmtrm_add_amount>12726675995</frmtrm_add_amount><ord>12</ord><currency>KRW</currency></list><list><rcept_no>20220513001393</rcept_no><reprt_code>11013</reprt_code><bsns_year>2022</bsns_year><corp_code>00508344</corp_code><sj_div>CIS</sj_div><sj_nm>포괄손익계산서</sj_nm><account_id>ifrs-full_OtherComprehensiveIncome</account_id><account_nm>기타포괄손익</account_nm><account_detail>-</account_detail><thstrm_nm>제 19 기 1분기</thstrm_nm><thstrm_amount>732155736</thstrm_amount><thstrm_add_amount>732155736</thstrm_add_amount><frmtrm_q_nm>제 18 기 1분기</frmtrm_q_nm><frmtrm_q_amount>-1097313116</frmtrm_q_amount><frmtrm_add_amount>-1097313116</frmtrm_add_amount><ord>13</ord><currency>KRW</currency></list><list><rcept_no>20220513001393</rcept_no><reprt_code>11013</reprt_code><bsns_year>2022</bsns_year><corp_code>00508344</corp_code><sj_div>CIS</sj_div><sj_nm>포괄손익계산서</sj_nm><account_id>dart_OtherComprehensiveIncomeThatWillBeReclassifiedToProfitOrLossNetOfTax</account_id><account_nm>후속적으로 당기손익으로 재분류되는 항목</account_nm><account_detail>-</account_detail><thstrm_nm>제 19 기 1분기</thstrm_nm><thstrm_amount>732155736</thstrm_amount><thstrm_add_amount>732155736</thstrm_add_amount><frmtrm_q_nm>제 18 기 1분기</frmtrm_q_nm><frmtrm_q_amount>-1097313116</frmtrm_q_amount><frmtrm_add_amount>-1097313116</frmtrm_add_amount><ord>14</ord><currency>KRW</currency></list><list><rcept_no>20220513001393</rcept_no><reprt_code>11013</reprt_code><bsns_year>2022</bsns_year><corp_code>00508344</corp_code><sj_div>CIS</sj_div><sj_nm>포괄손익계산서</sj_nm><account_id>ifrs-full_GainsLossesOnCashFlowHedgesNetOfTax</account_id><account_nm>파생상품평가이익</account_nm><account_detail>-</account_detail><thstrm_nm>제 19 기 1분기</thstrm_nm><thstrm_amount>732155736</thstrm_amount><thstrm_add_amount>732155736</thstrm_add_amount><frmtrm_q_nm>제 18 기 1분기</frmtrm_q_nm><frmtrm_q_amount>260404896</frmtrm_q_amount><frmtrm_add_amount>260404896</frmtrm_add_amount><ord>15</ord><currency>KRW</currency></list><list><rcept_no>20220513001393</rcept_no><reprt_code>11013</reprt_code><bsns_year>2022</bsns_year><corp_code>00508344</corp_code><sj_div>CIS</sj_div><sj_nm>포괄손익계산서</sj_nm><account_id>dart_ShareOfOtherComprehensiveIncomeOfAssociatesAndJointVenturesAccountedForUsingEquityMethodThatWillBeReclassifiedToProfitOrLossNetOfTax</account_id><account_nm>부의지분법자본변동</account_nm><account_detail>-</account_detail><thstrm_nm>제 19 기 1분기</thstrm_nm><thstrm_amount></thstrm_amount><thstrm_add_amount></thstrm_add_amount><frmtrm_q_nm>제 18 기 1분기</frmtrm_q_nm><frmtrm_q_amount>-1357718012</frmtrm_q_amount><frmtrm_add_amount>-1357718012</frmtrm_add_amount><ord>16</ord><currency>KRW</currency></list><list><rcept_no>20220513001393</rcept_no><reprt_code>11013</reprt_code><bsns_year>2022</bsns_year><corp_code>00508344</corp_code><sj_div>CIS</sj_div><sj_nm>포괄손익계산서</sj_nm><account_id>ifrs-full_ComprehensiveIncome</account_id><account_nm>총포괄이익</account_nm><account_detail>-</account_detail><thstrm_nm>제 19 기 1분기</thstrm_nm><thstrm_amount>31906157343</thstrm_amount><thstrm_add_amount>31906157343</thstrm_add_amount><frmtrm_q_nm>제 18 기 1분기</frmtrm_q_nm><frmtrm_q_amount>11629362879</frmtrm_q_amount><frmtrm_add_amount>11629362879</frmtrm_add_amount><ord>17</ord><currency>KRW</currency></list><list><rcept_no>20220513001393</rcept_no><reprt_code>11013</reprt_code><bsns_year>2022</bsns_year><corp_code>00508344</corp_code><sj_div>CIS</sj_div><sj_nm>포괄손익계산서</sj_nm><account_id>-표준계정코드 미사용-</account_id><account_nm>지배기업 소유주지분</account_nm><account_detail>-</account_detail><thstrm_nm>제 19 기 1분기</thstrm_nm><thstrm_amount>31068161439</thstrm_amount><thstrm_add_amount>31068161439</thstrm_add_amount><frmtrm_q_nm>제 18 기 1분기</frmtrm_q_nm><frmtrm_q_amount>12605711307</frmtrm_q_amount><frmtrm_add_amount>12605711307</frmtrm_add_amount><ord>19</ord><currency>KRW</currency></list><list><rcept_no>20220513001393</rcept_no><reprt_code>11013</reprt_code><bsns_year>2022</bsns_year><corp_code>00508344</corp_code><sj_div>CIS</sj_div><sj_nm>포괄손익계산서</sj_nm><account_id>-표준계정코드 미사용-</account_id><account_nm>비지배지분</account_nm><account_detail>-</account_detail><thstrm_nm>제 19 기 1분기</thstrm_nm><thstrm_amount>105840168</thstrm_amount><thstrm_add_amount>105840168</thstrm_add_amount><frmtrm_q_nm>제 18 기 1분기</frmtrm_q_nm><frmtrm_q_amount>120964688</frmtrm_q_amount><frmtrm_add_amount>120964688</frmtrm_add_amount><ord>20</ord><currency>KRW</currency></list><list><rcept_no>20220513001393</rcept_no><reprt_code>11013</reprt_code><bsns_year>2022</bsns_year><corp_code>00508344</corp_code><sj_div>CIS</sj_div><sj_nm>포괄손익계산서</sj_nm><account_id>ifrs-full_ComprehensiveIncomeAttributableToOwnersOfParent</account_id><account_nm>지배기업 소유주지분</account_nm><account_detail>-</account_detail><thstrm_nm>제 19 기 1분기</thstrm_nm><thstrm_amount>31800317175</thstrm_amount><thstrm_add_amount>31800317175</thstrm_add_amount><frmtrm_q_nm>제 18 기 1분기</frmtrm_q_nm><frmtrm_q_amount>11508398191</frmtrm_q_amount><frmtrm_add_amount>11508398191</frmtrm_add_amount><ord>22</ord><currency>KRW</currency></list><list><rcept_no>20220513001393</rcept_no><reprt_code>11013</reprt_code><bsns_year>2022</bsns_year><corp_code>00508344</corp_code><sj_div>CIS</sj_div><sj_nm>포괄손익계산서</sj_nm><account_id>ifrs-full_ComprehensiveIncomeAttributableToNoncontrollingInterests</account_id><account_nm>비지배지분</account_nm><account_detail>-</account_detail><thstrm_nm>제 19 기 1분기</thstrm_nm><thstrm_amount>105840168</thstrm_amount><thstrm_add_amount>105840168</thstrm_add_amount><frmtrm_q_nm>제 18 기 1분기</frmtrm_q_nm><frmtrm_q_amount>120964688</frmtrm_q_amount><frmtrm_add_amount>120964688</frmtrm_add_amount><ord>23</ord><currency>KRW</currency></list><list><rcept_no>20220513001393</rcept_no><reprt_code>11013</reprt_code><bsns_year>2022</bsns_year><corp_code>00508344</corp_code><sj_div>CIS</sj_div><sj_nm>포괄손익계산서</sj_nm><account_id>ifrs-full_BasicEarningsLossPerShare</account_id><account_nm>보통주 기본주당이익</account_nm><account_detail>-</account_detail><thstrm_nm>제 19 기 1분기</thstrm_nm><thstrm_amount>1264</thstrm_amount><thstrm_add_amount>1264</thstrm_add_amount><frmtrm_q_nm>제 18 기 1분기</frmtrm_q_nm><frmtrm_q_amount>467</frmtrm_q_amount><frmtrm_add_amount>467</frmtrm_add_amount><ord>25</ord><currency>KRW</currency></list><list><rcept_no>20220513001393</rcept_no><reprt_code>11013</reprt_code><bsns_year>2022</bsns_year><corp_code>00508344</corp_code><sj_div>CIS</sj_div><sj_nm>포괄손익계산서</sj_nm><account_id>ifrs-full_DilutedEarningsLossPerShare</account_id><account_nm>보통주 희석주당이익</account_nm><account_detail>-</account_detail><thstrm_nm>제 19 기 1분기</thstrm_nm><thstrm_amount>1263</thstrm_amount><thstrm_add_amount>1263</thstrm_add_amount><frmtrm_q_nm>제 18 기 1분기</frmtrm_q_nm><frmtrm_q_amount>465</frmtrm_q_amount><frmtrm_add_amount>465</frmtrm_add_amount><ord>26</ord><currency>KRW</currency></list><list><rcept_no>20220513001393</rcept_no><reprt_code>11013</reprt_code><bsns_year>2022</bsns_year><corp_code>00508344</corp_code><sj_div>CIS</sj_div><sj_nm>포괄손익계산서</sj_nm><account_id>-표준계정코드 미사용-</account_id><account_nm>우선주 기본주당이익</account_nm><account_detail>-</account_detail><thstrm_nm>제 19 기 1분기</thstrm_nm><thstrm_amount>1516</thstrm_amount><thstrm_add_amount>1516</thstrm_add_amount><frmtrm_q_nm>제 18 기 1분기</frmtrm_q_nm><frmtrm_q_amount>719</frmtrm_q_amount><frmtrm_add_amount>719</frmtrm_add_amount><ord>27</ord><currency>KRW</currency></list><list><rcept_no>20220513001393</rcept_no><reprt_code>11013</reprt_code><bsns_year>2022</bsns_year><corp_code>00508344</corp_code><sj_div>CIS</sj_div><sj_nm>포괄손익계산서</sj_nm><account_id>-표준계정코드 미사용-</account_id><account_nm>우선주 희석주당이익</account_nm><account_detail>-</account_detail><thstrm_nm>제 19 기 1분기</thstrm_nm><thstrm_amount>1515</thstrm_amount><thstrm_add_amount>1515</thstrm_add_amount><frmtrm_q_nm>제 18 기 1분기</frmtrm_q_nm><frmtrm_q_amount>717</frmtrm_q_amount><frmtrm_add_amount>717</frmtrm_add_amount><ord>28</ord><currency>KRW</currency></list><list><rcept_no>20220513001393</rcept_no><reprt_code>11013</reprt_code><bsns_year>2022</bsns_year><corp_code>00508344</corp_code><sj_div>CF</sj_div><sj_nm>현금흐름표</sj_nm><account_id>ifrs-full_CashFlowsFromUsedInOperatingActivities</account_id><account_nm>영업활동현금흐름</account_nm><account_detail>-</account_detail><thstrm_nm>제 19 기 1분기</thstrm_nm><thstrm_amount>-55717823875</thstrm_amount><frmtrm_q_nm>제 18 기 1분기</frmtrm_q_nm><frmtrm_q_amount>282369418500</frmtrm_q_amount><ord>0</ord><currency>KRW</currency></list><list><rcept_no>20220513001393</rcept_no><reprt_code>11013</reprt_code><bsns_year>2022</bsns_year><corp_code>00508344</corp_code><sj_div>CF</sj_div><sj_nm>현금흐름표</sj_nm><account_id>-표준계정코드 미사용-</account_id><account_nm>영업에서 창출된 현금</account_nm><account_detail>-</account_detail><thstrm_nm>제 19 기 1분기</thstrm_nm><thstrm_amount>-22603575085</thstrm_amount><frmtrm_q_nm>제 18 기 1분기</frmtrm_q_nm><frmtrm_q_amount>304990074525</frmtrm_q_amount><ord>1</ord><currency>KRW</currency></list><list><rcept_no>20220513001393</rcept_no><reprt_code>11013</reprt_code><bsns_year>2022</bsns_year><corp_code>00508344</corp_code><sj_div>CF</sj_div><sj_nm>현금흐름표</sj_nm><account_id>-표준계정코드 미사용-</account_id><account_nm>분기순이익</account_nm><account_detail>-</account_detail><thstrm_nm>제 19 기 1분기</thstrm_nm><thstrm_amount>31174001607</thstrm_amount><frmtrm_q_nm>제 18 기 1분기</frmtrm_q_nm><frmtrm_q_amount>12726675995</frmtrm_q_amount><ord>2</ord><currency>KRW</currency></list><list><rcept_no>20220513001393</rcept_no><reprt_code>11013</reprt_code><bsns_year>2022</bsns_year><corp_code>00508344</corp_code><sj_div>CF</sj_div><sj_nm>현금흐름표</sj_nm><account_id>-표준계정코드 미사용-</account_id><account_nm>조정</account_nm><account_detail>-</account_detail><thstrm_nm>제 19 기 1분기</thstrm_nm><thstrm_amount>23111937954</thstrm_amount><frmtrm_q_nm>제 18 기 1분기</frmtrm_q_nm><frmtrm_q_amount>24522093589</frmtrm_q_amount><ord>3</ord><currency>KRW</currency></list><list><rcept_no>20220513001393</rcept_no><reprt_code>11013</reprt_code><bsns_year>2022</bsns_year><corp_code>00508344</corp_code><sj_div>CF</sj_div><sj_nm>현금흐름표</sj_nm><account_id>-표준계정코드 미사용-</account_id><account_nm>영업활동의 자산부채의 변동</account_nm><account_detail>-</account_detail><thstrm_nm>제 19 기 1분기</thstrm_nm><thstrm_amount>-76889514646</thstrm_amount><frmtrm_q_nm>제 18 기 1분기</frmtrm_q_nm><frmtrm_q_amount>267741304941</frmtrm_q_amount><ord>4</ord><currency>KRW</currency></list><list><rcept_no>20220513001393</rcept_no><reprt_code>11013</reprt_code><bsns_year>2022</bsns_year><corp_code>00508344</corp_code><sj_div>CF</sj_div><sj_nm>현금흐름표</sj_nm><account_id>ifrs-full_DividendsReceivedClassifiedAsOperatingActivities</account_id><account_nm>배당금수취(영업)</account_nm><account_detail>-</account_detail><thstrm_nm>제 19 기 1분기</thstrm_nm><thstrm_amount>542654709</thstrm_amount><frmtrm_q_nm>제 18 기 1분기</frmtrm_q_nm><frmtrm_q_amount>372968256</frmtrm_q_amount><ord>5</ord><currency>KRW</currency></list><list><rcept_no>20220513001393</rcept_no><reprt_code>11013</reprt_code><bsns_year>2022</bsns_year><corp_code>00508344</corp_code><sj_div>CF</sj_div><sj_nm>현금흐름표</sj_nm><account_id>ifrs-full_InterestReceivedClassifiedAsOperatingActivities</account_id><account_nm>이자수취(영업)</account_nm><account_detail>-</account_detail><thstrm_nm>제 19 기 1분기</thstrm_nm><thstrm_amount>1281344764</thstrm_amount><frmtrm_q_nm>제 18 기 1분기</frmtrm_q_nm><frmtrm_q_amount>343651947</frmtrm_q_amount><ord>6</ord><currency>KRW</currency></list><list><rcept_no>20220513001393</rcept_no><reprt_code>11013</reprt_code><bsns_year>2022</bsns_year><corp_code>00508344</corp_code><sj_div>CF</sj_div><sj_nm>현금흐름표</sj_nm><account_id>ifrs-full_InterestPaidClassifiedAsOperatingActivities</account_id><account_nm>이자지급(영업)</account_nm><account_detail>-</account_detail><thstrm_nm>제 19 기 1분기</thstrm_nm><thstrm_amount>13091519027</thstrm_amount><frmtrm_q_nm>제 18 기 1분기</frmtrm_q_nm><frmtrm_q_amount>11499568664</frmtrm_q_amount><ord>7</ord><currency>KRW</currency></list><list><rcept_no>20220513001393</rcept_no><reprt_code>11013</reprt_code><bsns_year>2022</bsns_year><corp_code>00508344</corp_code><sj_div>CF</sj_div><sj_nm>현금흐름표</sj_nm><account_id>ifrs-full_IncomeTaxesPaidRefundClassifiedAsOperatingActivities</account_id><account_nm>법인세납부(환급)</account_nm><account_detail>-</account_detail><thstrm_nm>제 19 기 1분기</thstrm_nm><thstrm_amount>21846729236</thstrm_amount><frmtrm_q_nm>제 18 기 1분기</frmtrm_q_nm><frmtrm_q_amount>11837707564</frmtrm_q_amount><ord>8</ord><currency>KRW</currency></list><list><rcept_no>20220513001393</rcept_no><reprt_code>11013</reprt_code><bsns_year>2022</bsns_year><corp_code>00508344</corp_code><sj_div>CF</sj_div><sj_nm>현금흐름표</sj_nm><account_id>ifrs-full_CashFlowsFromUsedInInvestingActivities</account_id><account_nm>투자활동현금흐름</account_nm><account_detail>-</account_detail><thstrm_nm>제 19 기 1분기</thstrm_nm><thstrm_amount>-175710302169</thstrm_amount><frmtrm_q_nm>제 18 기 1분기</frmtrm_q_nm><frmtrm_q_amount>-141837184485</frmtrm_q_amount><ord>9</ord><currency>KRW</currency></list><list><rcept_no>20220513001393</rcept_no><reprt_code>11013</reprt_code><bsns_year>2022</bsns_year><corp_code>00508344</corp_code><sj_div>CF</sj_div><sj_nm>현금흐름표</sj_nm><account_id>dart_ProceedsFromSalesOfShortTermFinancialInstruments</account_id><account_nm>단기금융상품의 처분</account_nm><account_detail>-</account_detail><thstrm_nm>제 19 기 1분기</thstrm_nm><thstrm_amount>230082991366</thstrm_amount><frmtrm_q_nm>제 18 기 1분기</frmtrm_q_nm><frmtrm_q_amount>243661538819</frmtrm_q_amount><ord>10</ord><currency>KRW</currency></list><list><rcept_no>20220513001393</rcept_no><reprt_code>11013</reprt_code><bsns_year>2022</bsns_year><corp_code>00508344</corp_code><sj_div>CF</sj_div><sj_nm>현금흐름표</sj_nm><account_id>dart_PurchaseOfShortTermFinancialInstruments</account_id><account_nm>단기금융상품의 취득</account_nm><account_detail>-</account_detail><thstrm_nm>제 19 기 1분기</thstrm_nm><thstrm_amount>313072019289</thstrm_amount><frmtrm_q_nm>제 18 기 1분기</frmtrm_q_nm><frmtrm_q_amount>341749243994</frmtrm_q_amount><ord>11</ord><currency>KRW</currency></list><list><rcept_no>20220513001393</rcept_no><reprt_code>11013</reprt_code><bsns_year>2022</bsns_year><corp_code>00508344</corp_code><sj_div>CF</sj_div><sj_nm>현금흐름표</sj_nm><account_id>dart_ProceedsFromSalesOfLongTermFinancialInstruments</account_id><account_nm>장기금융상품의 처분</account_nm><account_detail>-</account_detail><thstrm_nm>제 19 기 1분기</thstrm_nm><thstrm_amount>186995791589</thstrm_amount><frmtrm_q_nm>제 18 기 1분기</frmtrm_q_nm><frmtrm_q_amount>90220213282</frmtrm_q_amount><ord>12</ord><currency>KRW</currency></list><list><rcept_no>20220513001393</rcept_no><reprt_code>11013</reprt_code><bsns_year>2022</bsns_year><corp_code>00508344</corp_code><sj_div>CF</sj_div><sj_nm>현금흐름표</sj_nm><account_id>dart_PurchaseOfLongTermFinancialInstruments</account_id><account_nm>장기금융상품의 취득</account_nm><account_detail>-</account_detail><thstrm_nm>제 19 기 1분기</thstrm_nm><thstrm_amount>190420369426</thstrm_amount><frmtrm_q_nm>제 18 기 1분기</frmtrm_q_nm><frmtrm_q_amount>76414484120</frmtrm_q_amount><ord>13</ord><currency>KRW</currency></list><list><rcept_no>20220513001393</rcept_no><reprt_code>11013</reprt_code><bsns_year>2022</bsns_year><corp_code>00508344</corp_code><sj_div>CF</sj_div><sj_nm>현금흐름표</sj_nm><account_id>dart_ProceedsFromSalesOfInvestmentsInAssociates</account_id><account_nm>관계기업투자의 처분</account_nm><account_detail>-</account_detail><thstrm_nm>제 19 기 1분기</thstrm_nm><thstrm_amount>32236329256</thstrm_amount><frmtrm_q_nm>제 18 기 1분기</frmtrm_q_nm><ord>14</ord><currency>KRW</currency></list><list><rcept_no>20220513001393</rcept_no><reprt_code>11013</reprt_code><bsns_year>2022</bsns_year><corp_code>00508344</corp_code><sj_div>CF</sj_div><sj_nm>현금흐름표</sj_nm><account_id>dart_PurchaseOfInvestmentsInAssociates</account_id><account_nm>관계기업투자의 취득</account_nm><account_detail>-</account_detail><thstrm_nm>제 19 기 1분기</thstrm_nm><thstrm_amount>79006762500</thstrm_amount><frmtrm_q_nm>제 18 기 1분기</frmtrm_q_nm><frmtrm_q_amount>14657968374</frmtrm_q_amount><ord>15</ord><currency>KRW</currency></list><list><rcept_no>20220513001393</rcept_no><reprt_code>11013</reprt_code><bsns_year>2022</bsns_year><corp_code>00508344</corp_code><sj_div>CF</sj_div><sj_nm>현금흐름표</sj_nm><account_id>dart_ProceedsFromSalesOfShortTermLoansAndReceivables</account_id><account_nm>단기대여금의 감소</account_nm><account_detail>-</account_detail><thstrm_nm>제 19 기 1분기</thstrm_nm><thstrm_amount>13261548320</thstrm_amount><frmtrm_q_nm>제 18 기 1분기</frmtrm_q_nm><frmtrm_q_amount>1000000000</frmtrm_q_amount><ord>16</ord><currency>KRW</currency></list><list><rcept_no>20220513001393</rcept_no><reprt_code>11013</reprt_code><bsns_year>2022</bsns_year><corp_code>00508344</corp_code><sj_div>CF</sj_div><sj_nm>현금흐름표</sj_nm><account_id>dart_PurchaseOfShortTermLoansAndReceivables</account_id><account_nm>단기대여금의 증가</account_nm><account_detail>-</account_detail><thstrm_nm>제 19 기 1분기</thstrm_nm><thstrm_amount>2105800000</thstrm_amount><frmtrm_q_nm>제 18 기 1분기</frmtrm_q_nm><frmtrm_q_amount>1273781157</frmtrm_q_amount><ord>17</ord><currency>KRW</currency></list><list><rcept_no>20220513001393</rcept_no><reprt_code>11013</reprt_code><bsns_year>2022</bsns_year><corp_code>00508344</corp_code><sj_div>CF</sj_div><sj_nm>현금흐름표</sj_nm><account_id>-표준계정코드 미사용-</account_id><account_nm>유동성장기대여금의 감소</account_nm><account_detail>-</account_detail><thstrm_nm>제 19 기 1분기</thstrm_nm><thstrm_amount>1248000</thstrm_amount><frmtrm_q_nm>제 18 기 1분기</frmtrm_q_nm><ord>18</ord><currency>KRW</currency></list><list><rcept_no>20220513001393</rcept_no><reprt_code>11013</reprt_code><bsns_year>2022</bsns_year><corp_code>00508344</corp_code><sj_div>CF</sj_div><sj_nm>현금흐름표</sj_nm><account_id>dart_ProceedsFromSalesOfLongTermLoansAndReceivables</account_id><account_nm>장기대여금의 감소</account_nm><account_detail>-</account_detail><thstrm_nm>제 19 기 1분기</thstrm_nm><thstrm_amount>8739576</thstrm_amount><frmtrm_q_nm>제 18 기 1분기</frmtrm_q_nm><frmtrm_q_amount>82654232</frmtrm_q_amount><ord>19</ord><currency>KRW</currency></list><list><rcept_no>20220513001393</rcept_no><reprt_code>11013</reprt_code><bsns_year>2022</bsns_year><corp_code>00508344</corp_code><sj_div>CF</sj_div><sj_nm>현금흐름표</sj_nm><account_id>dart_PurchaseOfLongTermLoansAndReceivables</account_id><account_nm>장기대여금의 증가</account_nm><account_detail>-</account_detail><thstrm_nm>제 19 기 1분기</thstrm_nm><thstrm_amount>850000000</thstrm_amount><frmtrm_q_nm>제 18 기 1분기</frmtrm_q_nm><ord>20</ord><currency>KRW</currency></list><list><rcept_no>20220513001393</rcept_no><reprt_code>11013</reprt_code><bsns_year>2022</bsns_year><corp_code>00508344</corp_code><sj_div>CF</sj_div><sj_nm>현금흐름표</sj_nm><account_id>ifrs-full_ProceedsFromSalesOfPropertyPlantAndEquipmentClassifiedAsInvestingActivities</account_id><account_nm>유형자산의 처분</account_nm><account_detail>-</account_detail><thstrm_nm>제 19 기 1분기</thstrm_nm><thstrm_amount>390000</thstrm_amount><frmtrm_q_nm>제 18 기 1분기</frmtrm_q_nm><frmtrm_q_amount>637926504</frmtrm_q_amount><ord>21</ord><currency>KRW</currency></list><list><rcept_no>20220513001393</rcept_no><reprt_code>11013</reprt_code><bsns_year>2022</bsns_year><corp_code>00508344</corp_code><sj_div>CF</sj_div><sj_nm>현금흐름표</sj_nm><account_id>ifrs-full_PurchaseOfPropertyPlantAndEquipmentClassifiedAsInvestingActivities</account_id><account_nm>유형자산의 취득</account_nm><account_detail>-</account_detail><thstrm_nm>제 19 기 1분기</thstrm_nm><thstrm_amount>51439074831</thstrm_amount><frmtrm_q_nm>제 18 기 1분기</frmtrm_q_nm><frmtrm_q_amount>44047650044</frmtrm_q_amount><ord>22</ord><currency>KRW</currency></list><list><rcept_no>20220513001393</rcept_no><reprt_code>11013</reprt_code><bsns_year>2022</bsns_year><corp_code>00508344</corp_code><sj_div>CF</sj_div><sj_nm>현금흐름표</sj_nm><account_id>ifrs-full_PurchaseOfIntangibleAssetsClassifiedAsInvestingActivities</account_id><account_nm>무형자산의 취득</account_nm><account_detail>-</account_detail><thstrm_nm>제 19 기 1분기</thstrm_nm><thstrm_amount>40400000</thstrm_amount><frmtrm_q_nm>제 18 기 1분기</frmtrm_q_nm><frmtrm_q_amount>16276480</frmtrm_q_amount><ord>23</ord><currency>KRW</currency></list><list><rcept_no>20220513001393</rcept_no><reprt_code>11013</reprt_code><bsns_year>2022</bsns_year><corp_code>00508344</corp_code><sj_div>CF</sj_div><sj_nm>현금흐름표</sj_nm><account_id>dart_ProceedsFromSalesOfFairValueFinancialAsset</account_id><account_nm>당기손익-공정가치측정 금융자산의 처분</account_nm><account_detail>-</account_detail><thstrm_nm>제 19 기 1분기</thstrm_nm><thstrm_amount>218132375</thstrm_amount><frmtrm_q_nm>제 18 기 1분기</frmtrm_q_nm><frmtrm_q_amount>719886847</frmtrm_q_amount><ord>24</ord><currency>KRW</currency></list><list><rcept_no>20220513001393</rcept_no><reprt_code>11013</reprt_code><bsns_year>2022</bsns_year><corp_code>00508344</corp_code><sj_div>CF</sj_div><sj_nm>현금흐름표</sj_nm><account_id>dart_PurchaseOfFairValueFinancialAsset</account_id><account_nm>당기손익-공정가치측정 금융자산의 취득</account_nm><account_detail>-</account_detail><thstrm_nm>제 19 기 1분기</thstrm_nm><thstrm_amount>50801518</thstrm_amount><frmtrm_q_nm>제 18 기 1분기</frmtrm_q_nm><ord>25</ord><currency>KRW</currency></list><list><rcept_no>20220513001393</rcept_no><reprt_code>11013</reprt_code><bsns_year>2022</bsns_year><corp_code>00508344</corp_code><sj_div>CF</sj_div><sj_nm>현금흐름표</sj_nm><account_id>dart_PurchaseOfInvestmentsInSubsidiariesJointVenturesAndAssociates</account_id><account_nm>연결범위변동에 따른 감소</account_nm><account_detail>-</account_detail><thstrm_nm>제 19 기 1분기</thstrm_nm><thstrm_amount>1530245087</thstrm_amount><frmtrm_q_nm>제 18 기 1분기</frmtrm_q_nm><ord>26</ord><currency>KRW</currency></list><list><rcept_no>20220513001393</rcept_no><reprt_code>11013</reprt_code><bsns_year>2022</bsns_year><corp_code>00508344</corp_code><sj_div>CF</sj_div><sj_nm>현금흐름표</sj_nm><account_id>ifrs-full_CashFlowsFromUsedInFinancingActivities</account_id><account_nm>재무활동현금흐름</account_nm><account_detail>-</account_detail><thstrm_nm>제 19 기 1분기</thstrm_nm><thstrm_amount>239459485376</thstrm_amount><frmtrm_q_nm>제 18 기 1분기</frmtrm_q_nm><frmtrm_q_amount>-91120789174</frmtrm_q_amount><ord>27</ord><currency>KRW</currency></list><list><rcept_no>20220513001393</rcept_no><reprt_code>11013</reprt_code><bsns_year>2022</bsns_year><corp_code>00508344</corp_code><sj_div>CF</sj_div><sj_nm>현금흐름표</sj_nm><account_id>dart_ProceedsFromShortTermBorrowings</account_id><account_nm>단기차입금의 차입</account_nm><account_detail>-</account_detail><thstrm_nm>제 19 기 1분기</thstrm_nm><thstrm_amount>1200000000</thstrm_amount><frmtrm_q_nm>제 18 기 1분기</frmtrm_q_nm><frmtrm_q_amount>38000000000</frmtrm_q_amount><ord>28</ord><currency>KRW</currency></list><list><rcept_no>20220513001393</rcept_no><reprt_code>11013</reprt_code><bsns_year>2022</bsns_year><corp_code>00508344</corp_code><sj_div>CF</sj_div><sj_nm>현금흐름표</sj_nm><account_id>dart_RepaymentsOfShortTermBorrowings</account_id><account_nm>단기차입금의 상환</account_nm><account_detail>-</account_detail><thstrm_nm>제 19 기 1분기</thstrm_nm><thstrm_amount></thstrm_amount><frmtrm_q_nm>제 18 기 1분기</frmtrm_q_nm><frmtrm_q_amount>17000000000</frmtrm_q_amount><ord>29</ord><currency>KRW</currency></list><list><rcept_no>20220513001393</rcept_no><reprt_code>11013</reprt_code><bsns_year>2022</bsns_year><corp_code>00508344</corp_code><sj_div>CF</sj_div><sj_nm>현금흐름표</sj_nm><account_id>-표준계정코드 미사용-</account_id><account_nm>유동성장기차입금의 차입</account_nm><account_detail>-</account_detail><thstrm_nm>제 19 기 1분기</thstrm_nm><thstrm_amount>2900000000</thstrm_amount><frmtrm_q_nm>제 18 기 1분기</frmtrm_q_nm><frmtrm_q_amount>9900000000</frmtrm_q_amount><ord>30</ord><currency>KRW</currency></list><list><rcept_no>20220513001393</rcept_no><reprt_code>11013</reprt_code><bsns_year>2022</bsns_year><corp_code>00508344</corp_code><sj_div>CF</sj_div><sj_nm>현금흐름표</sj_nm><account_id>-표준계정코드 미사용-</account_id><account_nm>유동성장기차입금의 상환</account_nm><account_detail>-</account_detail><thstrm_nm>제 19 기 1분기</thstrm_nm><thstrm_amount>6225594930</thstrm_amount><frmtrm_q_nm>제 18 기 1분기</frmtrm_q_nm><frmtrm_q_amount>247875449302</frmtrm_q_amount><ord>31</ord><currency>KRW</currency></list><list><rcept_no>20220513001393</rcept_no><reprt_code>11013</reprt_code><bsns_year>2022</bsns_year><corp_code>00508344</corp_code><sj_div>CF</sj_div><sj_nm>현금흐름표</sj_nm><account_id>dart_ProceedsFromLongTermBorrowings</account_id><account_nm>장기차입금의 차입</account_nm><account_detail>-</account_detail><thstrm_nm>제 19 기 1분기</thstrm_nm><thstrm_amount>259444000000</thstrm_amount><frmtrm_q_nm>제 18 기 1분기</frmtrm_q_nm><frmtrm_q_amount>248310000000</frmtrm_q_amount><ord>32</ord><currency>KRW</currency></list><list><rcept_no>20220513001393</rcept_no><reprt_code>11013</reprt_code><bsns_year>2022</bsns_year><corp_code>00508344</corp_code><sj_div>CF</sj_div><sj_nm>현금흐름표</sj_nm><account_id>dart_RepaymentsOfLongTermBorrowings</account_id><account_nm>장기차입금의 상환</account_nm><account_detail>-</account_detail><thstrm_nm>제 19 기 1분기</thstrm_nm><thstrm_amount>64802703821</thstrm_amount><frmtrm_q_nm>제 18 기 1분기</frmtrm_q_nm><frmtrm_q_amount>10200000000</frmtrm_q_amount><ord>33</ord><currency>KRW</currency></list><list><rcept_no>20220513001393</rcept_no><reprt_code>11013</reprt_code><bsns_year>2022</bsns_year><corp_code>00508344</corp_code><sj_div>CF</sj_div><sj_nm>현금흐름표</sj_nm><account_id>-표준계정코드 미사용-</account_id><account_nm>단기사채의 증가</account_nm><account_detail>-</account_detail><thstrm_nm>제 19 기 1분기</thstrm_nm><thstrm_amount></thstrm_amount><frmtrm_q_nm>제 18 기 1분기</frmtrm_q_nm><frmtrm_q_amount>129610000000</frmtrm_q_amount><ord>34</ord><currency>KRW</currency></list><list><rcept_no>20220513001393</rcept_no><reprt_code>11013</reprt_code><bsns_year>2022</bsns_year><corp_code>00508344</corp_code><sj_div>CF</sj_div><sj_nm>현금흐름표</sj_nm><account_id>-표준계정코드 미사용-</account_id><account_nm>단기사채의 상환</account_nm><account_detail>-</account_detail><thstrm_nm>제 19 기 1분기</thstrm_nm><thstrm_amount></thstrm_amount><frmtrm_q_nm>제 18 기 1분기</frmtrm_q_nm><frmtrm_q_amount>60000000000</frmtrm_q_amount><ord>35</ord><currency>KRW</currency></list><list><rcept_no>20220513001393</rcept_no><reprt_code>11013</reprt_code><bsns_year>2022</bsns_year><corp_code>00508344</corp_code><sj_div>CF</sj_div><sj_nm>현금흐름표</sj_nm><account_id>-표준계정코드 미사용-</account_id><account_nm>유동성사채의 증가</account_nm><account_detail>-</account_detail><thstrm_nm>제 19 기 1분기</thstrm_nm><thstrm_amount></thstrm_amount><frmtrm_q_nm>제 18 기 1분기</frmtrm_q_nm><frmtrm_q_amount>180000000000</frmtrm_q_amount><ord>36</ord><currency>KRW</currency></list><list><rcept_no>20220513001393</rcept_no><reprt_code>11013</reprt_code><bsns_year>2022</bsns_year><corp_code>00508344</corp_code><sj_div>CF</sj_div><sj_nm>현금흐름표</sj_nm><account_id>dart_ProceedsFromBonds</account_id><account_nm>비유동사채의 발행</account_nm><account_detail>-</account_detail><thstrm_nm>제 19 기 1분기</thstrm_nm><thstrm_amount>49850000000</thstrm_amount><frmtrm_q_nm>제 18 기 1분기</frmtrm_q_nm><ord>37</ord><currency>KRW</currency></list><list><rcept_no>20220513001393</rcept_no><reprt_code>11013</reprt_code><bsns_year>2022</bsns_year><corp_code>00508344</corp_code><sj_div>CF</sj_div><sj_nm>현금흐름표</sj_nm><account_id>ifrs-full_DividendsPaidClassifiedAsFinancingActivities</account_id><account_nm>배당금지급</account_nm><account_detail>-</account_detail><thstrm_nm>제 19 기 1분기</thstrm_nm><thstrm_amount>1074923781</thstrm_amount><frmtrm_q_nm>제 18 기 1분기</frmtrm_q_nm><frmtrm_q_amount>135242680</frmtrm_q_amount><ord>38</ord><currency>KRW</currency></list><list><rcept_no>20220513001393</rcept_no><reprt_code>11013</reprt_code><bsns_year>2022</bsns_year><corp_code>00508344</corp_code><sj_div>CF</sj_div><sj_nm>현금흐름표</sj_nm><account_id>ifrs-full_PaymentsOfFinanceLeaseLiabilitiesClassifiedAsFinancingActivities</account_id><account_nm>리스부채의 감소</account_nm><account_detail>-</account_detail><thstrm_nm>제 19 기 1분기</thstrm_nm><thstrm_amount>1831292092</thstrm_amount><frmtrm_q_nm>제 18 기 1분기</frmtrm_q_nm><frmtrm_q_amount>1730097192</frmtrm_q_amount><ord>39</ord><currency>KRW</currency></list><list><rcept_no>20220513001393</rcept_no><reprt_code>11013</reprt_code><bsns_year>2022</bsns_year><corp_code>00508344</corp_code><sj_div>CF</sj_div><sj_nm>현금흐름표</sj_nm><account_id>ifrs-full_IncreaseDecreaseInCashAndCashEquivalentsBeforeEffectOfExchangeRateChanges</account_id><account_nm>환율변동효과 반영전 현금및현금성자산의 순증가(감소)</account_nm><account_detail>-</account_detail><thstrm_nm>제 19 기 1분기</thstrm_nm><thstrm_amount>8031359332</thstrm_amount><frmtrm_q_nm>제 18 기 1분기</frmtrm_q_nm><frmtrm_q_amount>49411444841</frmtrm_q_amount><ord>40</ord><currency>KRW</currency></list><list><rcept_no>20220513001393</rcept_no><reprt_code>11013</reprt_code><bsns_year>2022</bsns_year><corp_code>00508344</corp_code><sj_div>CF</sj_div><sj_nm>현금흐름표</sj_nm><account_id>ifrs-full_EffectOfExchangeRateChangesOnCashAndCashEquivalents</account_id><account_nm>현금및현금성자산에 대한 환율변동효과</account_nm><account_detail>-</account_detail><thstrm_nm>제 19 기 1분기</thstrm_nm><thstrm_amount>136272403</thstrm_amount><frmtrm_q_nm>제 18 기 1분기</frmtrm_q_nm><frmtrm_q_amount>20716293</frmtrm_q_amount><ord>41</ord><currency>KRW</currency></list><list><rcept_no>20220513001393</rcept_no><reprt_code>11013</reprt_code><bsns_year>2022</bsns_year><corp_code>00508344</corp_code><sj_div>CF</sj_div><sj_nm>현금흐름표</sj_nm><account_id>ifrs-full_IncreaseDecreaseInCashAndCashEquivalents</account_id><account_nm>현금및현금성자산의순증가</account_nm><account_detail>-</account_detail><thstrm_nm>제 19 기 1분기</thstrm_nm><thstrm_amount>8167631735</thstrm_amount><frmtrm_q_nm>제 18 기 1분기</frmtrm_q_nm><frmtrm_q_amount>49432161134</frmtrm_q_amount><ord>42</ord><currency>KRW</currency></list><list><rcept_no>20220513001393</rcept_no><reprt_code>11013</reprt_code><bsns_year>2022</bsns_year><corp_code>00508344</corp_code><sj_div>CF</sj_div><sj_nm>현금흐름표</sj_nm><account_id>dart_CashAndCashEquivalentsAtBeginningOfPeriodCf</account_id><account_nm>기초현금및현금성자산</account_nm><account_detail>-</account_detail><thstrm_nm>제 19 기 1분기</thstrm_nm><thstrm_amount>70925668936</thstrm_amount><frmtrm_q_nm>제 18 기 1분기</frmtrm_q_nm><frmtrm_q_amount>58090644472</frmtrm_q_amount><ord>43</ord><currency>KRW</currency></list><list><rcept_no>20220513001393</rcept_no><reprt_code>11013</reprt_code><bsns_year>2022</bsns_year><corp_code>00508344</corp_code><sj_div>CF</sj_div><sj_nm>현금흐름표</sj_nm><account_id>dart_CashAndCashEquivalentsAtEndOfPeriodCf</account_id><account_nm>기말현금및현금성자산</account_nm><account_detail>-</account_detail><thstrm_nm>제 19 기 1분기</thstrm_nm><thstrm_amount>79093300671</thstrm_amount><frmtrm_q_nm>제 18 기 1분기</frmtrm_q_nm><frmtrm_q_amount>107522805606</frmtrm_q_amount><ord>44</ord><currency>KRW</currency></list><list><rcept_no>20220513001393</rcept_no><reprt_code>11013</reprt_code><bsns_year>2022</bsns_year><corp_code>00508344</corp_code><sj_div>SCE</sj_div><sj_nm>자본변동표</sj_nm><account_id>dart_EquityAtBeginningOfPeriod</account_id><account_nm>기초자본</account_nm><account_detail>자본 [member]|지배기업의 소유주에게 귀속되는 자본 [member]|자본금 [member]</account_detail><thstrm_nm>제 19 기 1분기</thstrm_nm><thstrm_amount>24190164000</thstrm_amount><frmtrm_q_nm>제 18 기 1분기</frmtrm_q_nm><frmtrm_q_amount>24190164000</frmtrm_q_amount><ord>1</ord><currency>KRW</currency></list><list><rcept_no>20220513001393</rcept_no><reprt_code>11013</reprt_code><bsns_year>2022</bsns_year><corp_code>00508344</corp_code><sj_div>SCE</sj_div><sj_nm>자본변동표</sj_nm><account_id>dart_EquityAtBeginningOfPeriod</account_id><account_nm>기초자본</account_nm><account_detail>자본 [member]|지배기업의 소유주에게 귀속되는 자본 [member]|이익잉여금 [member]</account_detail><thstrm_nm>제 19 기 1분기</thstrm_nm><thstrm_amount>328087900969</thstrm_amount><frmtrm_q_nm>제 18 기 1분기</frmtrm_q_nm><frmtrm_q_amount>213976327749</frmtrm_q_amount><ord>1</ord><currency>KRW</currency></list><list><rcept_no>20220513001393</rcept_no><reprt_code>11013</reprt_code><bsns_year>2022</bsns_year><corp_code>00508344</corp_code><sj_div>SCE</sj_div><sj_nm>자본변동표</sj_nm><account_id>dart_EquityAtBeginningOfPeriod</account_id><account_nm>기초자본</account_nm><account_detail>자본 [member]|지배기업의 소유주에게 귀속되는 자본 [member]|기타포괄손익누계액 [member]</account_detail><thstrm_nm>제 19 기 1분기</thstrm_nm><thstrm_amount>113949643</thstrm_amount><frmtrm_q_nm>제 18 기 1분기</frmtrm_q_nm><frmtrm_q_amount>-10963876785</frmtrm_q_amount><ord>1</ord><currency>KRW</currency></list><list><rcept_no>20220513001393</rcept_no><reprt_code>11013</reprt_code><bsns_year>2022</bsns_year><corp_code>00508344</corp_code><sj_div>SCE</sj_div><sj_nm>자본변동표</sj_nm><account_id>dart_EquityAtBeginningOfPeriod</account_id><account_nm>기초자본</account_nm><account_detail>자본 [member]|지배기업의 소유주에게 귀속되는 자본 [member]|기타자본</account_detail><thstrm_nm>제 19 기 1분기</thstrm_nm><thstrm_amount>-3940549139</thstrm_amount><frmtrm_q_nm>제 18 기 1분기</frmtrm_q_nm><frmtrm_q_amount>6389493981</frmtrm_q_amount><ord>1</ord><currency>KRW</currency></list><list><rcept_no>20220513001393</rcept_no><reprt_code>11013</reprt_code><bsns_year>2022</bsns_year><corp_code>00508344</corp_code><sj_div>SCE</sj_div><sj_nm>자본변동표</sj_nm><account_id>dart_EquityAtBeginningOfPeriod</account_id><account_nm>기초자본</account_nm><account_detail>자본 [member]|지배기업의 소유주에게 귀속되는 자본 [member]</account_detail><thstrm_nm>제 19 기 1분기</thstrm_nm><thstrm_amount>639256047752</thstrm_amount><frmtrm_q_nm>제 18 기 1분기</frmtrm_q_nm><frmtrm_q_amount>524396691224</frmtrm_q_amount><ord>1</ord><currency>KRW</currency></list><list><rcept_no>20220513001393</rcept_no><reprt_code>11013</reprt_code><bsns_year>2022</bsns_year><corp_code>00508344</corp_code><sj_div>SCE</sj_div><sj_nm>자본변동표</sj_nm><account_id>dart_EquityAtBeginningOfPeriod</account_id><account_nm>기초자본</account_nm><account_detail>자본 [member]|비지배지분 [member]</account_detail><thstrm_nm>제 19 기 1분기</thstrm_nm><thstrm_amount></thstrm_amount><frmtrm_q_nm>제 18 기 1분기</frmtrm_q_nm><frmtrm_q_amount>7075057217</frmtrm_q_amount><ord>1</ord><currency>KRW</currency></list><list><rcept_no>20220513001393</rcept_no><reprt_code>11013</reprt_code><bsns_year>2022</bsns_year><corp_code>00508344</corp_code><sj_div>SCE</sj_div><sj_nm>자본변동표</sj_nm><account_id>dart_EquityAtBeginningOfPeriod</account_id><account_nm>기초자본</account_nm><account_detail>자본 [member]|지배기업의 소유주에게 귀속되는 자본 [member]|자본잉여금 [member]</account_detail><thstrm_nm>제 19 기 1분기</thstrm_nm><thstrm_amount>290804582279</thstrm_amount><frmtrm_q_nm>제 18 기 1분기</frmtrm_q_nm><frmtrm_q_amount>290804582279</frmtrm_q_amount><ord>1</ord><currency>KRW</currency></list><list><rcept_no>20220513001393</rcept_no><reprt_code>11013</reprt_code><bsns_year>2022</bsns_year><corp_code>00508344</corp_code><sj_div>SCE</sj_div><sj_nm>자본변동표</sj_nm><account_id>dart_EquityAtBeginningOfPeriod</account_id><account_nm>기초자본</account_nm><account_detail>연결재무제표 [member]</account_detail><thstrm_nm>제 19 기 1분기</thstrm_nm><thstrm_amount>639256047752</thstrm_amount><frmtrm_q_nm>제 18 기 1분기</frmtrm_q_nm><frmtrm_q_amount>531471748441</frmtrm_q_amount><ord>1</ord><currency>KRW</currency></list><list><rcept_no>20220513001393</rcept_no><reprt_code>11013</reprt_code><bsns_year>2022</bsns_year><corp_code>00508344</corp_code><sj_div>SCE</sj_div><sj_nm>자본변동표</sj_nm><account_id>ifrs-full_ProfitLoss</account_id><account_nm>분기순이익</account_nm><account_detail>자본 [member]|지배기업의 소유주에게 귀속되는 자본 [member]</account_detail><thstrm_nm>제 19 기 1분기</thstrm_nm><thstrm_amount>31068161439</thstrm_amount><frmtrm_q_nm>제 18 기 1분기</frmtrm_q_nm><frmtrm_q_amount>12605711307</frmtrm_q_amount><ord>2</ord><currency>KRW</currency></list><list><rcept_no>20220513001393</rcept_no><reprt_code>11013</reprt_code><bsns_year>2022</bsns_year><corp_code>00508344</corp_code><sj_div>SCE</sj_div><sj_nm>자본변동표</sj_nm><account_id>ifrs-full_ProfitLoss</account_id><account_nm>분기순이익</account_nm><account_detail>자본 [member]|지배기업의 소유주에게 귀속되는 자본 [member]|이익잉여금 [member]</account_detail><thstrm_nm>제 19 기 1분기</thstrm_nm><thstrm_amount>31068161439</thstrm_amount><frmtrm_q_nm>제 18 기 1분기</frmtrm_q_nm><frmtrm_q_amount>12605711307</frmtrm_q_amount><ord>2</ord><currency>KRW</currency></list><list><rcept_no>20220513001393</rcept_no><reprt_code>11013</reprt_code><bsns_year>2022</bsns_year><corp_code>00508344</corp_code><sj_div>SCE</sj_div><sj_nm>자본변동표</sj_nm><account_id>ifrs-full_ProfitLoss</account_id><account_nm>분기순이익</account_nm><account_detail>자본 [member]|비지배지분 [member]</account_detail><thstrm_nm>제 19 기 1분기</thstrm_nm><thstrm_amount>105840168</thstrm_amount><frmtrm_q_nm>제 18 기 1분기</frmtrm_q_nm><frmtrm_q_amount>120964688</frmtrm_q_amount><ord>2</ord><currency>KRW</currency></list><list><rcept_no>20220513001393</rcept_no><reprt_code>11013</reprt_code><bsns_year>2022</bsns_year><corp_code>00508344</corp_code><sj_div>SCE</sj_div><sj_nm>자본변동표</sj_nm><account_id>ifrs-full_ProfitLoss</account_id><account_nm>분기순이익</account_nm><account_detail>연결재무제표 [member]</account_detail><thstrm_nm>제 19 기 1분기</thstrm_nm><thstrm_amount>31174001607</thstrm_amount><frmtrm_q_nm>제 18 기 1분기</frmtrm_q_nm><frmtrm_q_amount>12726675995</frmtrm_q_amount><ord>2</ord><currency>KRW</currency></list><list><rcept_no>20220513001393</rcept_no><reprt_code>11013</reprt_code><bsns_year>2022</bsns_year><corp_code>00508344</corp_code><sj_div>SCE</sj_div><sj_nm>자본변동표</sj_nm><account_id>-표준계정코드 미사용-</account_id><account_nm>파생상품평가이익</account_nm><account_detail>연결재무제표 [member]</account_detail><thstrm_nm>제 19 기 1분기</thstrm_nm><thstrm_amount>732155736</thstrm_amount><frmtrm_q_nm>제 18 기 1분기</frmtrm_q_nm><frmtrm_q_amount>260404896</frmtrm_q_amount><ord>3</ord><currency>KRW</currency></list><list><rcept_no>20220513001393</rcept_no><reprt_code>11013</reprt_code><bsns_year>2022</bsns_year><corp_code>00508344</corp_code><sj_div>SCE</sj_div><sj_nm>자본변동표</sj_nm><account_id>-표준계정코드 미사용-</account_id><account_nm>파생상품평가이익</account_nm><account_detail>자본 [member]|지배기업의 소유주에게 귀속되는 자본 [member]</account_detail><thstrm_nm>제 19 기 1분기</thstrm_nm><thstrm_amount>732155736</thstrm_amount><frmtrm_q_nm>제 18 기 1분기</frmtrm_q_nm><frmtrm_q_amount>260404896</frmtrm_q_amount><ord>3</ord><currency>KRW</currency></list><list><rcept_no>20220513001393</rcept_no><reprt_code>11013</reprt_code><bsns_year>2022</bsns_year><corp_code>00508344</corp_code><sj_div>SCE</sj_div><sj_nm>자본변동표</sj_nm><account_id>-표준계정코드 미사용-</account_id><account_nm>파생상품평가이익</account_nm><account_detail>자본 [member]|지배기업의 소유주에게 귀속되는 자본 [member]|기타포괄손익누계액 [member]</account_detail><thstrm_nm>제 19 기 1분기</thstrm_nm><thstrm_amount>732155736</thstrm_amount><frmtrm_q_nm>제 18 기 1분기</frmtrm_q_nm><frmtrm_q_amount>260404896</frmtrm_q_amount><ord>3</ord><currency>KRW</currency></list><list><rcept_no>20220513001393</rcept_no><reprt_code>11013</reprt_code><bsns_year>2022</bsns_year><corp_code>00508344</corp_code><sj_div>SCE</sj_div><sj_nm>자본변동표</sj_nm><account_id>-표준계정코드 미사용-</account_id><account_nm>부의지분법자본변동</account_nm><account_detail>자본 [member]|지배기업의 소유주에게 귀속되는 자본 [member]|기타자본</account_detail><thstrm_nm>제 19 기 1분기</thstrm_nm><thstrm_amount>7146148836</thstrm_amount><frmtrm_q_nm>제 18 기 1분기</frmtrm_q_nm><ord>4</ord><currency>KRW</currency></list><list><rcept_no>20220513001393</rcept_no><reprt_code>11013</reprt_code><bsns_year>2022</bsns_year><corp_code>00508344</corp_code><sj_div>SCE</sj_div><sj_nm>자본변동표</sj_nm><account_id>-표준계정코드 미사용-</account_id><account_nm>부의지분법자본변동</account_nm><account_detail>자본 [member]|지배기업의 소유주에게 귀속되는 자본 [member]</account_detail><thstrm_nm>제 19 기 1분기</thstrm_nm><thstrm_amount>7146148836</thstrm_amount><frmtrm_q_nm>제 18 기 1분기</frmtrm_q_nm><frmtrm_q_amount>-1357718012</frmtrm_q_amount><ord>4</ord><currency>KRW</currency></list><list><rcept_no>20220513001393</rcept_no><reprt_code>11013</reprt_code><bsns_year>2022</bsns_year><corp_code>00508344</corp_code><sj_div>SCE</sj_div><sj_nm>자본변동표</sj_nm><account_id>-표준계정코드 미사용-</account_id><account_nm>부의지분법자본변동</account_nm><account_detail>연결재무제표 [member]</account_detail><thstrm_nm>제 19 기 1분기</thstrm_nm><thstrm_amount>7146148836</thstrm_amount><frmtrm_q_nm>제 18 기 1분기</frmtrm_q_nm><frmtrm_q_amount>-1357718012</frmtrm_q_amount><ord>4</ord><currency>KRW</currency></list><list><rcept_no>20220513001393</rcept_no><reprt_code>11013</reprt_code><bsns_year>2022</bsns_year><corp_code>00508344</corp_code><sj_div>SCE</sj_div><sj_nm>자본변동표</sj_nm><account_id>-표준계정코드 미사용-</account_id><account_nm>부의지분법자본변동</account_nm><account_detail>자본 [member]|지배기업의 소유주에게 귀속되는 자본 [member]|기타포괄손익누계액 [member]</account_detail><thstrm_nm>제 19 기 1분기</thstrm_nm><thstrm_amount></thstrm_amount><frmtrm_q_nm>제 18 기 1분기</frmtrm_q_nm><frmtrm_q_amount>-1357718012</frmtrm_q_amount><ord>4</ord><currency>KRW</currency></list><list><rcept_no>20220513001393</rcept_no><reprt_code>11013</reprt_code><bsns_year>2022</bsns_year><corp_code>00508344</corp_code><sj_div>SCE</sj_div><sj_nm>자본변동표</sj_nm><account_id>ifrs-full_DividendsPaid</account_id><account_nm>연차배당</account_nm><account_detail>자본 [member]|지배기업의 소유주에게 귀속되는 자본 [member]|이익잉여금 [member]</account_detail><thstrm_nm>제 19 기 1분기</thstrm_nm><thstrm_amount>19795619200</thstrm_amount><frmtrm_q_nm>제 18 기 1분기</frmtrm_q_nm><frmtrm_q_amount>16708114400</frmtrm_q_amount><ord>5</ord><currency>KRW</currency></list><list><rcept_no>20220513001393</rcept_no><reprt_code>11013</reprt_code><bsns_year>2022</bsns_year><corp_code>00508344</corp_code><sj_div>SCE</sj_div><sj_nm>자본변동표</sj_nm><account_id>ifrs-full_DividendsPaid</account_id><account_nm>연차배당</account_nm><account_detail>자본 [member]|지배기업의 소유주에게 귀속되는 자본 [member]</account_detail><thstrm_nm>제 19 기 1분기</thstrm_nm><thstrm_amount>19795619200</thstrm_amount><frmtrm_q_nm>제 18 기 1분기</frmtrm_q_nm><frmtrm_q_amount>16708114400</frmtrm_q_amount><ord>5</ord><currency>KRW</currency></list><list><rcept_no>20220513001393</rcept_no><reprt_code>11013</reprt_code><bsns_year>2022</bsns_year><corp_code>00508344</corp_code><sj_div>SCE</sj_div><sj_nm>자본변동표</sj_nm><account_id>ifrs-full_DividendsPaid</account_id><account_nm>연차배당</account_nm><account_detail>자본 [member]|비지배지분 [member]</account_detail><thstrm_nm>제 19 기 1분기</thstrm_nm><thstrm_amount></thstrm_amount><frmtrm_q_nm>제 18 기 1분기</frmtrm_q_nm><frmtrm_q_amount>135242679</frmtrm_q_amount><ord>5</ord><currency>KRW</currency></list><list><rcept_no>20220513001393</rcept_no><reprt_code>11013</reprt_code><bsns_year>2022</bsns_year><corp_code>00508344</corp_code><sj_div>SCE</sj_div><sj_nm>자본변동표</sj_nm><account_id>ifrs-full_DividendsPaid</account_id><account_nm>연차배당</account_nm><account_detail>연결재무제표 [member]</account_detail><thstrm_nm>제 19 기 1분기</thstrm_nm><thstrm_amount>19795619200</thstrm_amount><frmtrm_q_nm>제 18 기 1분기</frmtrm_q_nm><frmtrm_q_amount>16843357079</frmtrm_q_amount><ord>5</ord><currency>KRW</currency></list><list><rcept_no>20220513001393</rcept_no><reprt_code>11013</reprt_code><bsns_year>2022</bsns_year><corp_code>00508344</corp_code><sj_div>SCE</sj_div><sj_nm>자본변동표</sj_nm><account_id>dart_ShareBasedPaymentTransactions</account_id><account_nm>주식매수선택권</account_nm><account_detail>자본 [member]|지배기업의 소유주에게 귀속되는 자본 [member]|기타자본</account_detail><thstrm_nm>제 19 기 1분기</thstrm_nm><thstrm_amount>97195000</thstrm_amount><frmtrm_q_nm>제 18 기 1분기</frmtrm_q_nm><ord>6</ord><currency>KRW</currency></list><list><rcept_no>20220513001393</rcept_no><reprt_code>11013</reprt_code><bsns_year>2022</bsns_year><corp_code>00508344</corp_code><sj_div>SCE</sj_div><sj_nm>자본변동표</sj_nm><account_id>dart_ShareBasedPaymentTransactions</account_id><account_nm>주식매수선택권</account_nm><account_detail>자본 [member]|지배기업의 소유주에게 귀속되는 자본 [member]</account_detail><thstrm_nm>제 19 기 1분기</thstrm_nm><thstrm_amount>97195000</thstrm_amount><frmtrm_q_nm>제 18 기 1분기</frmtrm_q_nm><ord>6</ord><currency>KRW</currency></list><list><rcept_no>20220513001393</rcept_no><reprt_code>11013</reprt_code><bsns_year>2022</bsns_year><corp_code>00508344</corp_code><sj_div>SCE</sj_div><sj_nm>자본변동표</sj_nm><account_id>dart_ShareBasedPaymentTransactions</account_id><account_nm>주식매수선택권</account_nm><account_detail>연결재무제표 [member]</account_detail><thstrm_nm>제 19 기 1분기</thstrm_nm><thstrm_amount>97195000</thstrm_amount><frmtrm_q_nm>제 18 기 1분기</frmtrm_q_nm><ord>6</ord><currency>KRW</currency></list><list><rcept_no>20220513001393</rcept_no><reprt_code>11013</reprt_code><bsns_year>2022</bsns_year><corp_code>00508344</corp_code><sj_div>SCE</sj_div><sj_nm>자본변동표</sj_nm><account_id>dart_OtherTransactions</account_id><account_nm>기타거래</account_nm><account_detail>자본 [member]|비지배지분 [member]</account_detail><thstrm_nm>제 19 기 1분기</thstrm_nm><thstrm_amount>-105840168</thstrm_amount><frmtrm_q_nm>제 18 기 1분기</frmtrm_q_nm><ord>7</ord><currency>KRW</currency></list><list><rcept_no>20220513001393</rcept_no><reprt_code>11013</reprt_code><bsns_year>2022</bsns_year><corp_code>00508344</corp_code><sj_div>SCE</sj_div><sj_nm>자본변동표</sj_nm><account_id>dart_OtherTransactions</account_id><account_nm>기타거래</account_nm><account_detail>연결재무제표 [member]</account_detail><thstrm_nm>제 19 기 1분기</thstrm_nm><thstrm_amount>232028420</thstrm_amount><frmtrm_q_nm>제 18 기 1분기</frmtrm_q_nm><frmtrm_q_amount>-396848064</frmtrm_q_amount><ord>7</ord><currency>KRW</currency></list><list><rcept_no>20220513001393</rcept_no><reprt_code>11013</reprt_code><bsns_year>2022</bsns_year><corp_code>00508344</corp_code><sj_div>SCE</sj_div><sj_nm>자본변동표</sj_nm><account_id>dart_OtherTransactions</account_id><account_nm>기타거래</account_nm><account_detail>자본 [member]|지배기업의 소유주에게 귀속되는 자본 [member]</account_detail><thstrm_nm>제 19 기 1분기</thstrm_nm><thstrm_amount>337868588</thstrm_amount><frmtrm_q_nm>제 18 기 1분기</frmtrm_q_nm><frmtrm_q_amount>-396848064</frmtrm_q_amount><ord>7</ord><currency>KRW</currency></list><list><rcept_no>20220513001393</rcept_no><reprt_code>11013</reprt_code><bsns_year>2022</bsns_year><corp_code>00508344</corp_code><sj_div>SCE</sj_div><sj_nm>자본변동표</sj_nm><account_id>dart_OtherTransactions</account_id><account_nm>기타거래</account_nm><account_detail>자본 [member]|지배기업의 소유주에게 귀속되는 자본 [member]|이익잉여금 [member]</account_detail><thstrm_nm>제 19 기 1분기</thstrm_nm><thstrm_amount>337868588</thstrm_amount><frmtrm_q_nm>제 18 기 1분기</frmtrm_q_nm><frmtrm_q_amount>-396848064</frmtrm_q_amount><ord>7</ord><currency>KRW</currency></list><list><rcept_no>20220513001393</rcept_no><reprt_code>11013</reprt_code><bsns_year>2022</bsns_year><corp_code>00508344</corp_code><sj_div>SCE</sj_div><sj_nm>자본변동표</sj_nm><account_id>ifrs-full_ChangesInEquity</account_id><account_nm>자본 증가(감소) 합계</account_nm><account_detail>자본 [member]|지배기업의 소유주에게 귀속되는 자본 [member]|이익잉여금 [member]</account_detail><thstrm_nm>제 19 기 1분기</thstrm_nm><thstrm_amount>11610410827</thstrm_amount><frmtrm_q_nm>제 18 기 1분기</frmtrm_q_nm><frmtrm_q_amount>-4499251157</frmtrm_q_amount><ord>8</ord><currency>KRW</currency></list><list><rcept_no>20220513001393</rcept_no><reprt_code>11013</reprt_code><bsns_year>2022</bsns_year><corp_code>00508344</corp_code><sj_div>SCE</sj_div><sj_nm>자본변동표</sj_nm><account_id>ifrs-full_ChangesInEquity</account_id><account_nm>자본 증가(감소) 합계</account_nm><account_detail>자본 [member]|지배기업의 소유주에게 귀속되는 자본 [member]|기타자본</account_detail><thstrm_nm>제 19 기 1분기</thstrm_nm><thstrm_amount>7243343836</thstrm_amount><frmtrm_q_nm>제 18 기 1분기</frmtrm_q_nm><ord>8</ord><currency>KRW</currency></list><list><rcept_no>20220513001393</rcept_no><reprt_code>11013</reprt_code><bsns_year>2022</bsns_year><corp_code>00508344</corp_code><sj_div>SCE</sj_div><sj_nm>자본변동표</sj_nm><account_id>ifrs-full_ChangesInEquity</account_id><account_nm>자본 증가(감소) 합계</account_nm><account_detail>자본 [member]|지배기업의 소유주에게 귀속되는 자본 [member]</account_detail><thstrm_nm>제 19 기 1분기</thstrm_nm><thstrm_amount>19585910399</thstrm_amount><frmtrm_q_nm>제 18 기 1분기</frmtrm_q_nm><frmtrm_q_amount>-5596564273</frmtrm_q_amount><ord>8</ord><currency>KRW</currency></list><list><rcept_no>20220513001393</rcept_no><reprt_code>11013</reprt_code><bsns_year>2022</bsns_year><corp_code>00508344</corp_code><sj_div>SCE</sj_div><sj_nm>자본변동표</sj_nm><account_id>ifrs-full_ChangesInEquity</account_id><account_nm>자본 증가(감소) 합계</account_nm><account_detail>자본 [member]|지배기업의 소유주에게 귀속되는 자본 [member]|기타포괄손익누계액 [member]</account_detail><thstrm_nm>제 19 기 1분기</thstrm_nm><thstrm_amount>732155736</thstrm_amount><frmtrm_q_nm>제 18 기 1분기</frmtrm_q_nm><frmtrm_q_amount>-1097313116</frmtrm_q_amount><ord>8</ord><currency>KRW</currency></list><list><rcept_no>20220513001393</rcept_no><reprt_code>11013</reprt_code><bsns_year>2022</bsns_year><corp_code>00508344</corp_code><sj_div>SCE</sj_div><sj_nm>자본변동표</sj_nm><account_id>ifrs-full_ChangesInEquity</account_id><account_nm>자본 증가(감소) 합계</account_nm><account_detail>연결재무제표 [member]</account_detail><thstrm_nm>제 19 기 1분기</thstrm_nm><thstrm_amount>19585910399</thstrm_amount><frmtrm_q_nm>제 18 기 1분기</frmtrm_q_nm><frmtrm_q_amount>-5610842264</frmtrm_q_amount><ord>8</ord><currency>KRW</currency></list><list><rcept_no>20220513001393</rcept_no><reprt_code>11013</reprt_code><bsns_year>2022</bsns_year><corp_code>00508344</corp_code><sj_div>SCE</sj_div><sj_nm>자본변동표</sj_nm><account_id>ifrs-full_ChangesInEquity</account_id><account_nm>자본 증가(감소) 합계</account_nm><account_detail>자본 [member]|비지배지분 [member]</account_detail><thstrm_nm>제 19 기 1분기</thstrm_nm><thstrm_amount></thstrm_amount><frmtrm_q_nm>제 18 기 1분기</frmtrm_q_nm><frmtrm_q_amount>-14277991</frmtrm_q_amount><ord>8</ord><currency>KRW</currency></list><list><rcept_no>20220513001393</rcept_no><reprt_code>11013</reprt_code><bsns_year>2022</bsns_year><corp_code>00508344</corp_code><sj_div>SCE</sj_div><sj_nm>자본변동표</sj_nm><account_id>ifrs-full_Equity</account_id><account_nm>기말자본</account_nm><account_detail>자본 [member]|지배기업의 소유주에게 귀속되는 자본 [member]|자본잉여금 [member]</account_detail><thstrm_nm>제 19 기 1분기</thstrm_nm><thstrm_amount>290804582279</thstrm_amount><frmtrm_q_nm>제 18 기 1분기</frmtrm_q_nm><frmtrm_q_amount>290804582279</frmtrm_q_amount><ord>9</ord><currency>KRW</currency></list><list><rcept_no>20220513001393</rcept_no><reprt_code>11013</reprt_code><bsns_year>2022</bsns_year><corp_code>00508344</corp_code><sj_div>SCE</sj_div><sj_nm>자본변동표</sj_nm><account_id>ifrs-full_Equity</account_id><account_nm>기말자본</account_nm><account_detail>자본 [member]|지배기업의 소유주에게 귀속되는 자본 [member]|자본금 [member]</account_detail><thstrm_nm>제 19 기 1분기</thstrm_nm><thstrm_amount>24190164000</thstrm_amount><frmtrm_q_nm>제 18 기 1분기</frmtrm_q_nm><frmtrm_q_amount>24190164000</frmtrm_q_amount><ord>9</ord><currency>KRW</currency></list><list><rcept_no>20220513001393</rcept_no><reprt_code>11013</reprt_code><bsns_year>2022</bsns_year><corp_code>00508344</corp_code><sj_div>SCE</sj_div><sj_nm>자본변동표</sj_nm><account_id>ifrs-full_Equity</account_id><account_nm>기말자본</account_nm><account_detail>자본 [member]|지배기업의 소유주에게 귀속되는 자본 [member]|이익잉여금 [member]</account_detail><thstrm_nm>제 19 기 1분기</thstrm_nm><thstrm_amount>339698311796</thstrm_amount><frmtrm_q_nm>제 18 기 1분기</frmtrm_q_nm><frmtrm_q_amount>209477076592</frmtrm_q_amount><ord>9</ord><currency>KRW</currency></list><list><rcept_no>20220513001393</rcept_no><reprt_code>11013</reprt_code><bsns_year>2022</bsns_year><corp_code>00508344</corp_code><sj_div>SCE</sj_div><sj_nm>자본변동표</sj_nm><account_id>ifrs-full_Equity</account_id><account_nm>기말자본</account_nm><account_detail>자본 [member]|지배기업의 소유주에게 귀속되는 자본 [member]|기타자본</account_detail><thstrm_nm>제 19 기 1분기</thstrm_nm><thstrm_amount>3302794697</thstrm_amount><frmtrm_q_nm>제 18 기 1분기</frmtrm_q_nm><frmtrm_q_amount>6389493981</frmtrm_q_amount><ord>9</ord><currency>KRW</currency></list><list><rcept_no>20220513001393</rcept_no><reprt_code>11013</reprt_code><bsns_year>2022</bsns_year><corp_code>00508344</corp_code><sj_div>SCE</sj_div><sj_nm>자본변동표</sj_nm><account_id>ifrs-full_Equity</account_id><account_nm>기말자본</account_nm><account_detail>자본 [member]|지배기업의 소유주에게 귀속되는 자본 [member]</account_detail><thstrm_nm>제 19 기 1분기</thstrm_nm><thstrm_amount>658841958151</thstrm_amount><frmtrm_q_nm>제 18 기 1분기</frmtrm_q_nm><frmtrm_q_amount>518800126951</frmtrm_q_amount><ord>9</ord><currency>KRW</currency></list><list><rcept_no>20220513001393</rcept_no><reprt_code>11013</reprt_code><bsns_year>2022</bsns_year><corp_code>00508344</corp_code><sj_div>SCE</sj_div><sj_nm>자본변동표</sj_nm><account_id>ifrs-full_Equity</account_id><account_nm>기말자본</account_nm><account_detail>자본 [member]|비지배지분 [member]</account_detail><thstrm_nm>제 19 기 1분기</thstrm_nm><thstrm_amount></thstrm_amount><frmtrm_q_nm>제 18 기 1분기</frmtrm_q_nm><frmtrm_q_amount>7060779226</frmtrm_q_amount><ord>9</ord><currency>KRW</currency></list><list><rcept_no>20220513001393</rcept_no><reprt_code>11013</reprt_code><bsns_year>2022</bsns_year><corp_code>00508344</corp_code><sj_div>SCE</sj_div><sj_nm>자본변동표</sj_nm><account_id>ifrs-full_Equity</account_id><account_nm>기말자본</account_nm><account_detail>연결재무제표 [member]</account_detail><thstrm_nm>제 19 기 1분기</thstrm_nm><thstrm_amount>658841958151</thstrm_amount><frmtrm_q_nm>제 18 기 1분기</frmtrm_q_nm><frmtrm_q_amount>525860906177</frmtrm_q_amount><ord>9</ord><currency>KRW</currency></list><list><rcept_no>20220513001393</rcept_no><reprt_code>11013</reprt_code><bsns_year>2022</bsns_year><corp_code>00508344</corp_code><sj_div>SCE</sj_div><sj_nm>자본변동표</sj_nm><account_id>ifrs-full_Equity</account_id><account_nm>기말자본</account_nm><account_detail>자본 [member]|지배기업의 소유주에게 귀속되는 자본 [member]|기타포괄손익누계액 [member]</account_detail><thstrm_nm>제 19 기 1분기</thstrm_nm><thstrm_amount>846105379</thstrm_amount><frmtrm_q_nm>제 18 기 1분기</frmtrm_q_nm><frmtrm_q_amount>-12061189901</frmtrm_q_amount><ord>9</ord><currency>KRW</currency></list></result>